Workbook
Name Slicer_Membership: #N/A
Name Slicer_Payment_Mode: #N/A
Name Slicer_Region: #N/A
Name Slicer_Return_Status: #N/A
Name Slicer_Sales_Channel: #N/A

Sheet Supplier
A1: Supplier_ID | B1: Supplier_Name | C1: Contact_Person | D1: Phone | E1: Email | F1: City | G1: Lead_Time_Days | H1: Rating | I1: Status
A2: SUP001 | B2: Anna Agro Pvt Ltd | C2: Madhavan Rao | D2: 9826600539 | E2: madhavan.anna@agromail.com | F2: Salem | G2: 4 | H2: 4.3 | I2: Active
A3: SUP002 | B3: Palani Suppliers Pvt Ltd | C3: Kamala Subramaniam | D3: 9349817734 | E3: kamala.palani@suppliersmail.com | F3: Coimbatore | G3: 2 | H3: 2.7 | I3: Active
A4: SUP003 | B4: Saravana Beverages Pvt Ltd | C4: Hari Mudaliar | D4: 9732719211 | E4: hari.saravana@beveragesmail.com | F4: Kochi | G4: 8 | H4: 3.1 | I4: Active
A5: SUP004 | B5: Coastal Household Products Pvt Ltd | C5: Aishwarya Naicker | D5: 9398362082 | E5: aishwarya.coastal@householdmail.com | F5: Madurai | G5: 13 | H5: 3.6 | I5: Active
A6: SUP005 | B6: Vel Traders Pvt Ltd | C6: Padma Raj | D6: 9469319644 | E6: padma.vel@bizcom | F6: Chennai | G6: 8 | H6: 2.7 | I6: Active
A7: SUP006 | B7: Kovai Distributors Pvt Ltd | C7: Vasanthi Venkataraman | D7: 9506448196 | E7: vasanthi.kovai@distributorsmail.com | F7: Kochi | G7: 45 | H7: 4.9 | I7: Active
A8: SUP007 | B8: Om Fresh Produce Pvt Ltd | C8: Raghav Prabhu | D8: 9174684276 | E8: raghav.om@freshmail.com | F8: Tiruppur | G8: 11 | H8: 3 | I8: Active
A9: SUP008 | B9: Sree Snacks Co Pvt Ltd | C9: Naveen Devi | D9: 9398471886 | E9: naveen.sree@snacksmail.com | F9: Salem | G9: 15 | H9: 2.8 | I9: Active
A10: SUP009 | B10: Ganesh Snacks Co Pvt Ltd | C10: Chitra Gupta | D10: 9853573823 | E10: chitra.ganesh@snacksmail.com | F10: Tiruppur | G10: 5 | H10: 4.2 | I10: Active
A11: SUP010 | B11: Bharat Snacks Co Pvt Ltd | C11: Raghav Pillai | D11: 9596348124 | E11: raghav.bharat@snacksmail.com | F11: Kochi | G11: 13 | H11: 3.1 | I11: Active
A12: SUP011 | B12: Malabar Distributors Pvt Ltd | C12: Nandhini Mudaliar | D12: 9924970419 | E12: nandhini.malabar@distributorsmail.com | F12: Kochi | G12: 5 | H12: 4.2 | I12: Active
A13: SUP012 | B13: Tirupati Foods Pvt Ltd | C13: Karthik Naicker | D13: 9326541099 | E13: karthik.tirupati@foodsmail.com | F13: Tiruppur | G13: 8 | H13: 3.2 | I13: Active
... A86: SUP085 | B86: Anna Traders Pvt Ltd | C86: Ezhil Menon | D86: 9707665448 | E86: ezhil.anna@tradersmail.com | F86: Hyderabad | G86: 14 | H86: 2.8 | I86: Active

Sheet Store
A1: Store_ID | B1: Store_Name | C1: Manager | D1: Region | E1: City | F1: State | G1: Store_Type | H1: Opening_Date | I1: Monthly_Target | J1: Status
A2: STR001 | B2: FreshMart Madurai Crossing | C2: Sudha Naicker | D2: South | E2: Madurai | F2: Tamil Nadu | G2: Supermarket | H2: 42147 | I2: 1921769 | J2: Active
A3: STR002 | B3: FreshMart Tiruppur Bypass | C3: Manoj Nair | D3: South | E3: Tiruppur | F3: Tamil Nadu | G3: Convenience | H3: 42633 | I3: 591044 | J3: Active
A4: STR003 | B4: FreshMart Tiruppur Square | C4: Suresh Nathan | D4: South | E4: Tiruppur | F4: Tamil Nadu | G4: Express | H4: 44173 | I4: 890380 | J4: Active
A5: STR004 | B5: FreshMart Erode Plaza | C5: Prakash Kumar | D5: South | E5: Erode | F5: Tamil Nadu | G5: Convenience | H5: 44049 | I5: 584869 | J5: Active
A6: STR005 | B6: FreshMart Chennai Crossing | C6: Lokesh Mudaliar | D6: South | E6: Chennai | F6: Tamil Nadu | G6: Express | H6: 42883 | I6: 983603 | J6: Active
A7: STR006 | B7: FreshMart Mysuru Junction | C7: Senthil Sekar | D7: South | E7: Mysuru | F7: Karnataka | G7: Supermarket | H7: 43856 | I7: 2561982 | J7: Active
A8: STR007 | B8: FreshMart Mysuru Towers | C8: Sudha Sekar | D8: South | E8: Mysuru | F8: Karnataka | G8: Express | H8: 44740 | I8: 988505 | J8: Active
A9: STR008 | B9: FreshMart Kochi Plaza | C9: Malathi Sekar | D9: South | E9: Kochi | F9: Kerala | G9: Supermarket | H9: 44920 | I9: 2481146 | J9: Active
A10: STR009 | B10: FreshMart Kochi Square | C10: Hari Naicker | D10: South | E10: Kochi | F10: Kerala | G10: Convenience | H10: 42974 | I10: 429599 | J10: Active
A11: STR010 | B11: FreshMart Kochi Colony | C11: Bhuvana Naicker | D11: South | E11: Kochi | F11: Kerala | G11: Hypermarket | H11: 42536 | I11: 3928553 | J11: Active
A12: STR011 | B12: FreshMart Bengaluru Enclave | C12: Vasanthi Chandran | D12: South | E12: Bengaluru | F12: Karnataka | G12: Convenience | H12: 43687 | I12: 569084 | J12: Active
A13: STR012 | B13: FreshMart Chennai Junction | C13: Pandi Varma | D13: South | E13: Chennai | F13: Tamil Nadu | G13: Convenience | H13: 43848 | I13: 544019 | J13: Active
... A181: STR180 | B181: FreshMart Guwahati Extension | C181: Suresh Naidu | D181: East | E181: Guwahati | F181: Assam | G181: Hypermarket | H181: 44575 | I181: 4606432 | J181: Active

Sheet Products
A1: Product_ID | B1: Product_Name | C1: Category | D1: Subcategory | E1: Brand | F1: Cost_Price | G1: Selling_Price | H1: Supplier_ID | I1: Season | J1: Status
A2: PRD001 | B2: Local Bakers Buns 1kg | C2: Bakery | D2: Buns | E2: Local Bakers | F2: 184.74 | G2: 299.73 | H2: SUP059 | I2: Summer | J2: Active
A3: PRD002 | B3: Britannia Buns Pack | C3: Bakery | D3: Buns | E3: Britannia | F3: 254.05 | G3: 440.5 | H3: SUP062 | I3: Monsoon | J3: Active
A4: PRD003 | B4: Harvest Gold Buns Combo | C4: Bakery | D4: Buns | E4: Harvest Gold | F4: 343.65 | G4: 589.75 | H4: SUP012 | I4: Winter | J4: Active
A5: PRD004 | B5: Britannia Buns 2kg | C5: Bakery | D5: Buns | E5: Britannia | F5: 236.54 | G5: 398.25 | H5: SUP044 | I5: All Season | J5: Active
A6: PRD005 | B6: Amul Paneer 250ml | C6: Bakery | D6: Buns | E6: Harvest Gold | F6: 205.27 | G6: 332.74 | H6: SUP034 | I6: Winter | J6: Active
A7: PRD006 | B7: Harvest Gold Cookies 500g | C7: Bakery | D7: Cookies | E7: Harvest Gold | F7: 216.32 | G7: 343.56 | H7: SUP031 | I7: Monsoon | J7: Active
A8: PRD007 | B8: Britannia Buns 2kg v2 | C8: Bakery | D8: Buns | E8: Britannia | F8: 265.44 | G8: 437.49 | H8: SUP003 | I8: All Season | J8: Active
A9: PRD008 | B9: Britannia Cookies 200g | C9: Bakery | D9: Cookies | E9: Britannia | F9: 282.88 | G9: 455.79 | H9: SUP075 | I9: Winter | J9: Active
A10: PRD009 | B10: Harvest Gold Buns 200g | C10: Bakery | D10: Buns | E10: Harvest Gold | F10: 398.72 | G10: 661.91 | H10: SUP046 | I10: Monsoon | J10: Active
A11: PRD010 | B11: Harvest Gold Cookies Pack | C11: Bakery | D11: Cookies | E11: Harvest Gold | F11: 107.6 | G11: 182.3 | H11: SUP041 | I11: All Season | J11: Active
A12: PRD011 | B12: Britannia Rusk 1L | C12: Bakery | D12: Rusk | E12: Britannia | F12: 102.23 | G12: 168.36 | H12: SUP076 | I12: Festive | J12: Active
A13: PRD012 | B13: Harvest Gold Rusk 1kg | C13: Bakery | D13: Rusk | E13: Harvest Gold | F13: 336.4 | G13: 541.35 | H13: SUP047 | I13: Summer | J13: Active
... A151: PRD150 | B151: Lizol Toilet Cleaner 200g v2 | C151: Cleaning | D151: Toilet Cleaner | E151: Lizol | F151: 158.06 | G151: 214.04 | H151: SUP021 | I151: All Season | J151: Active

Sheet Employee
A1: Employee_ID | B1: Employee_Name | C1: Gender | D1: Department | E1: Salary | F1: Joining_Date | G1: Store_ID | H1: Employment_Status
A2: EMP0332 | B2: Udhay Gounder | C2: Male | D2: Cashier | E2: 14073 | F2: 42542 | G2: STR149 | H2: Active
A3: EMP0340 | B3: Nithya Subramaniam | C3: Female | D3: Cashier | E3: 14174 | F3: 45193 | G3: STR097 | H3: Active
A4: EMP0157 | B4: Elango Velan | C4: Male | D4: Cashier | E4: 14183 | F4: 43368 | G4: STR012 | H4: Active
A5: EMP0213 | B5: Venkat Varma | C5: Male | D5: Cashier | E5: 14562 | F5: 42739 | G5: STR141 | H5: Active
A6: EMP0319 | B6: Harini Kumar | C6: Female | D6: Cashier | E6: 14584 | F6: 44594 | G6: STR121 | H6: Active
A7: EMP0263 | B7: Vani Nair | C7: Female | D7: Cashier | E7: 14788 | F7: 44212 | G7: STR086 | H7: Active
A8: EMP0018 | B8: Chandran Kumar | C8: Male | D8: Cashier | E8: 14882 | F8: 45471 | G8: STR107 | H8: Active
A9: EMP0058 | B9: Senthil Raj | C9: Male | D9: Cashier | E9: 14977 | F9: 43915 | G9: STR011 | H9: Active
A10: EMP0321 | B10: Sundar Velan | C10: Male | D10: Cashier | E10: 14999 | F10: 45516 | G10: STR064 | H10: Active
A11: EMP0121 | B11: Nithya Selvam | C11: Female | D11: Cashier | E11: 15100 | F11: 45153 | G11: STR085 | H11: Active
A12: EMP0029 | B12: Vasanthi Menon | C12: Female | D12: Cashier | E12: 15131 | F12: 44060 | G12: STR155 | H12: Active
A13: EMP0125 | B13: Nandhini Chettiar | C13: Female | D13: Cashier | E13: 15146 | F13: 46020 | G13: STR138 | H13: Active
... A351: EMP0047 | B351: Sundar Gounder | C351: Male | D351: Store Manager | E351: 67135 | F351: 45398 | G351: STR144 | H351: Active

Sheet Customer
A1: Customer_ID | B1: Customer_Name | C1: Gender | D1: DOB | E1: Phone | F1: Email | G1: City | H1: State | I1: Region | J1: Membership | K1: Registration_Date
A2: CUST0001 | B2: Revathi Balan | C2: Female | D2: 31272 | E2: 9204528821 | F2: revathi1@gmail.com | G2: Coimbatore | H2: Tamil Nadu | I2: South | J2: Bronze | K2: 44659
A3: CUST0002 | B3: Eswari Murugan | C3: Female | D3: 21939 | E3: 9362238769 | F3: eswari2@gmail.com | G3: Tiruppur | H3: Tamil Nadu | I3: South | J3: Silver | K3: 45809
A4: CUST0003 | B4: Banu Balan | C4: Female | D4: 22236 | E4: 9222912620 | F4: banu3@gmail.com | G4: Erode | H4: Tamil Nadu | I4: South | J4: Bronze | K4: 44349
A5: CUST0004 | B5: Naveen Sharma | C5: Male | D5: 21314 | E5: 9806272779 | F5: naveen4@gmail.com | G5: Coimbatore | H5: Tamil Nadu | I5: South | J5: Silver | K5: 44988
A6: CUST0005 | B6: Pandi Raj | C6: Male | D6: 35481 | E6: 9123876200 | F6: pandi5@gmail.com | G6: Guwahati | H6: Assam | I6: East | J6: Silver | K6: 45509
A7: CUST0006 | B7: Thiru Devi | C7: Male | D7: 38850 | E7: 9967934041 | F7: thiru6@gmail.com | G7: Kanpur | H7: Uttar Pradesh | I7: North | J7: Silver | K7: 43501
A8: CUST0007 | B8: Senthil Pillai | C8: Male | D8: 36564 | E8: 9464577685 | F8: senthil7@gmail.com | G8: Salem | H8: Tamil Nadu | I8: South | J8: Silver | K8: 45834
A9: CUST0008 | B9: Eswari Raj | C9: Female | D9: 34376 | E9: 9633597839 | F9: eswari8@gmail.com | G9: Erode | H9: Tamil Nadu | I9: South | J9: Silver | K9: 43927
A10: CUST0009 | B10: Mani Nair | C10: Male | D10: 37648 | E10: 9408545686 | F10: mani9@gmail.com | G10: Chennai | H10: Tamil Nadu | I10: South | J10: Bronze | K10: 43977
A11: CUST0010 | B11: Tara Achari | C11: Female | D11: 33263 | E11: 9770629385 | F11: tara10@gmail.com | G11: Erode | H11: Tamil Nadu | I11: South | J11: Bronze | K11: 44026
A12: CUST0011 | B12: Prasath Mudaliar | C12: Male | D12: 39036 | E12: 9735509839 | F12: prasath11@gmail.com | G12: Chennai | H12: Tamil Nadu | I12: South | J12: Bronze | K12: 43489
A13: CUST0012 | B13: Meena Gupta | C13: Female | D13: 37491 | E13: 9558601461 | F13: meena12@gmail.com | G13: Chennai | H13: Tamil Nadu | I13: South | J13: Bronze | K13: 45047
... A293: CUST0292 | B293: Nirmala Venkataraman | C293: Female | D293: 25491 | E293: 9322664095 | F293: nirmala292@gmail.com | G293: Tiruppur | H293: Tamil Nadu | I293: South | J293: Silver | K293: 44136
A294: CUST0293 | B294: Suresh Chandran | C294: Male | D294: 35225 | E294: 9468999657 | F294: suresh293@gmail.com | G294: Mysuru | H294: Karnataka | J294: Gold | K294: 44662
A295: CUST0294 | B295: Deepak Venkataraman | C295: Male | D295: 20441 | E295: 9223139628 | F295: deepak294@gmail.com | G295: Salem | H295: Tamil Nadu | I295: South | J295: Silver | K295: 44127
A296: CUST0295 | B296: Latha Gounder | C296: Female | D296: 35302 | E296: 9595378308 | F296: latha295@gmail.com | G296: Madurai | H296: Tamil Nadu | I296: South | J296: Silver | K296: 45086
A297: CUST0296 | B297: Uma Pandian | C297: Female | D297: 34433 | E297: 9605504475 | F297: uma296@gmail.com | G297: Kochi | H297: Kerala | I297: South | J297: Bronze | K297: 43675
A298: CUST0297 | B298: Nithya Sharma | C298: Female | D298: 20681 | E298: 9207927292 | F298: nithya297@gmail.com | G298: Madurai | H298: Tamil Nadu | I298: South | J298: Gold | K298: 45587
A299: CUST0298 | B299: Divya Naicker | C299: Female | D299: 32897 | E299: 9183306581 | F299: divya298@gmail.com | G299: Chennai | H299: Tamil Nadu | I299: South | J299: Silver | K299: 43790
A300: CUST0299 | B300: Chandran Krishnan | C300: Male | D300: 25119 | E300: 9484492979 | F300: chandran299@gmail.com | G300: Coimbatore | H300: Tamil Nadu | I300: South | J300: Bronze | K300: 44905
A301: CUST0300 | B301: Indira Prabhu | C301: Female | D301: 37532 | E301: 9574656314 | F301: indira300@gmail.com | G301: Coimbatore | H301: Tamil Nadu | I301: South | J301: Bronze | K301: 43986
A302: CUST0301 | B302: Dinesh Chandran | C302: Male | D302: 23458 | E302: 9841254136 | F302: dinesh301@gmail.com | G302: Kochi | H302: Kerala | I302: South | J302: Bronze | K302: 44700
A303: CUST0302 | B303: Rajesh Reddy | C303: Male | D303: 21684 | E303: 9923682643 | F303: rajesh302@gmail.com | G303: Coimbatore | H303: Tamil Nadu | I303: South | J303: Bronze | K303: 44646
A304: CUST0303 | B304: Kamala Subramaniam | C304: Female | D304: 27906 | E304: 9198125433 | F304: kamala303@gmail.com | G304: Salem | H304: Tamil Nadu | I304: South | J304: Silver | K304: 43920
A305: CUST0304 | B305: Missing Customer Name | C305: Female | D305: 31136 | E305: 9830100976 | F305: yamuna304@gmail.com | G305: Coimbatore | H305: Tamil Nadu | I305: South | J305: Bronze | K305: 43888
A306: CUST0305 | B306: Hemalatha Mudaliar | C306: Female | D306: 23255 | E306: 9280262874 | F306: hemalatha305@gmail.com | G306: Salem | H306: Tamil Nadu | I306: South | J306: Bronze | K306: 45821
... A446: CUST0445 | B446: Anjali Kumar | C446: Female | D446: 20380 | E446: 9562572075 | F446: anjali445@gmail.com | G446: Madurai | H446: Tamil Nadu | I446: South | J446: Silver | K446: 43516
A447: CUST0446 | B447: Ramesh Sharma | C447: Male | D447: 25126 | E447: 9232975024 | F447: ramesh446@gmail.com | G447: Chennai | H447: Tamil Nadu | J447: Silver | K447: 44783
A448: CUST0447 | B448: Harini Krishnan | C448: Female | D448: 28286 | E448: 9605408862 | F448: harini447@gmail.com | G448: Pune | H448: Maharashtra | I448: West | J448: Bronze | K448: 44027
A449: CUST0448 | B449: Sanjay Achari | C449: Male | D449: 26059 | E449: 9971388578 | F449: sanjay448@gmail.com | G449: Erode | H449: Tamil Nadu | I449: South | J449: Silver | K449: 45298
A450: CUST0449 | B450: Sudha Sekar | C450: Female | D450: 34486 | E450: 9250188999 | F450: sudha449@gmail.com | G450: Mysuru | H450: Karnataka | I450: South | J450: Bronze | K450: 43763
A451: CUST0450 | B451: Bhavani Chettiar | C451: Female | D451: 26593 | E451: 9303546093 | F451: bhavani450@gmail.com | G451: Bengaluru | H451: Karnataka | I451: South | J451: Gold | K451: 43554
A452: CUST0451 | B452: Divya Nair | C452: Female | D452: 30943 | E452: 9272134233 | F452: divya451@gmail.com | G452: Madurai | H452: Tamil Nadu | I452: South | J452: Silver | K452: 43230
A453: CUST0452 | B453: Dhanya Varma | C453: Female | D453: 28799 | E453: 9552147658 | F453: dhanya452@gmail.com | G453: Mysuru | H453: Karnataka | I453: South | J453: Bronze | K453: 43587
A454: CUST0453 | B454: Prasath Nair | C454: Male | D454: 24265 | E454: 9906476640 | F454: prasath453@gmail.com | G454: Mysuru | H454: Karnataka | I454: South | J454: Bronze | K454: 44431
A455: CUST0454 | B455: Raghav Nair | C455: Male | D455: 32831 | E455: 9217824679 | F455: raghav454@gmail.com | G455: Bengaluru | H455: Karnataka | I455: South | J455: Silver | K455: 43639
A456: CUST0455 | B456: Nithya Venkataraman | C456: Female | D456: 36474 | E456: 9923973312 | F456: nithya455@gmail.com | G456: Pune | H456: Maharashtra | I456: West | J456: Gold | K456: 43156
A457: CUST0456 | B457: Kamala Devi | C457: Female | D457: 31301 | E457: 9741117091 | F457: kamala456@gmail.com | G457: Coimbatore | H457: Tamil Nadu | I457: South | J457: Bronze | K457: 44860
A458: CUST0457 | B458: Nithya Raj | C458: Female | D458: 29337 | E458: 9188707067 | F458: nithya457@gmail.com | G458: Bengaluru | H458: Karnataka | I458: South | J458: Silver | K458: 45091
A459: CUST0458 | B459: Prasath Rao | C459: Male | D459: 36842 | E459: 9367862922 | F459: prasath458@gmail.com | G459: Salem | H459: Tamil Nadu | I459: South | J459: Bronze | K459: 43866
... A701: CUST0700 | B701: Radha Naicker | C701: Female | D701: 21870 | E701: 9158725903 | F701: radha700@gmail.com | G701: Kochi | H701: Kerala | I701: South | J701: Silver | K701: 43447

Sheet Sheet2
A3: Count of Sales_Amount
A4: 2500

Sheet Sheet4
E1: Monthly Sales & Profit Trend
A3: Row Labels | B3: Sum of Profit | C3: Sum of Sales_Amount
A4: Jan | B4: 29980.87 | C4: 121730.91
A5: Feb | B5: 43151.69 | C5: 169237.23
A6: Mar | B6: 61610.78 | C6: 243357.27
A7: Apr | B7: 50155.37 | C7: 195249.44
A8: May | B8: 61161.92 | C8: 223829.24
A9: Jun | B9: 58096.27 | C9: 226577.54
A10: Jul | B10: 42067 | C10: 171047.56
A11: Aug | B11: 49379.88 | C11: 193434.23
A12: Sep | B12: 58943.03 | C12: 239642.24
A13: Oct | B13: 115133.04 | C13: 445171.86
A14: Nov | B14: 79014.61 | C14: 303499.88
A15: Dec | B15: 88664.43 | C15: 335655.2
A16: Grand Total | B16: 737358.89 | C16: 2868432.6

Sheet Dashboard KPI'S
A1: KPI | B1: Formula/Source
A2: Total Sales | B2: =SUM(Sales_Transactions!S:S) -> 2868432.6
A3: Total Profit | B3: =SUM(Sales_Transactions!U:U) -> 737358.89
A4: Profit Margin % | B4: ='Dashboard KPI''S'!B3/ 'Dashboard KPI''S'!B2 -> 0.25705986
A5: Units Sold | B5: =SUM(Sales_Transactions!O:O) -> 9823
A6: Return Rate % | B6: =COUNTIF(Sales_Transactions!W:W,"Returned")/COUNTA(Sales_Transactions!A:A) -> 0.045581767

Sheet Dashboard
A1: FRESHMART SALES & PROFIT DASHBOARD
AI17: c

Sheet Sheet3
A3: Row Labels | B3: Sum of Profit | C3: Count of Sales_Amount
A4: Chandrasekar Balan | B4: 6856.31 | C4: 12
A5: Deepa Kumar | B5: 6900.51 | C5: 12
A6: Dhanush Mudaliar | B6: 7149.96 | C6: 9
A7: Elango Nair | B7: 8434.49 | C7: 15
A8: Hema Gounder | B8: 6674.2 | C8: 13
A9: Kalpana Gounder | B9: 7296.34 | C9: 8
A10: Lalitha Nathan | B10: 9206.16 | C10: 16
A11: Lokesh Gupta | B11: 6645.31 | C11: 11
A12: Missing Customer Name | B12: 7430.79 | C12: 33
A13: Nithya Sharma | B13: 7732.72 | C13: 12

Sheet Sheet1

Sheet Sales_Transactions
A1: Invoice_Number | B1: Transaction_Date | C1: Customer_ID | D1: Customer Name | E1: Membership | F1: Product_ID | G1: Product Name | H1: Catogory | I1: Store_ID | J1: Store Name | K1: Region | L1: Employee_ID | M1: Employee Name | N1: Department | O1: Quantity | P1: Unit_Price | Q1: Discount_Pct | R1: Discount_Amount | S1: Sales_Amount | T1: Cost_Amount | U1: Profit | V1: Payment_Mode | W1: Return_Status | X1: Sales_Channel | Y1: Order_Time | Z1: Day_Type
A2: INV100252 | B2: 45767 | C2: CUST0567 | D2: =_xlfn.XLOOKUP(Sales_Transactions!$C2,Customer!$A$2:$A$701,Customer!$B$2:$B$701,"Missing") -> Bharath Balan | E2: =_xlfn.XLOOKUP(Table14[[#This Row],[Customer_ID]],Table10[Customer_ID],Table10[Membership],"Missing Membership") -> Gold | F2: PRD018 | G2: =_xlfn.XLOOKUP(Sales_Transactions!$F2,Products!$A$2:$A$151,Products!$B$2:$B$151,"missing product") -> Aavin Cheese 200g | H2: =_xlfn.XLOOKUP(Sales_Transactions!$F2,Table9[Product_ID],Table9[Category],"Missing Catogory") -> Dairy | I2: STR046 | J2: =_xlfn.XLOOKUP(Sales_Transactions!$I2,Store!$A$2:$A$181,Store!$B$2:$B$181,"Missing Store") -> FreshMart Mysuru Colony | K2: =_xlfn.XLOOKUP(Sales_Transactions!$I2,Store!$A$2:$A$181,Store!$D$2:$D$181,"East") -> South | L2: EMP0191 | M2: Thenmozhi Krishnan | N2: =_xlfn.XLOOKUP(Sales_Transactions!$L2,Table12[Employee_ID],Table12[Department],"Missing Department") -> Billing | O2: 8 | P2: 238.51 | Q2: 0 | R2: 0 | S2: 2194.29 | T2: 1529.6 | U2: 664.69 | V2: Debit Card | W2: Returned | X2: Mobile App | Y2: 19:14 | Z2: Weekend
A3: INV100360 | B3: 45825 | C3: CUST0669 | D3: =_xlfn.XLOOKUP(Sales_Transactions!$C3,Customer!$A$2:$A$701,Customer!$B$2:$B$701,"Missing") -> Mani Krishnan | E3: =_xlfn.XLOOKUP(Table14[[#This Row],[Customer_ID]],Table10[Customer_ID],Table10[Membership],"Missing Membership") -> Silver | F3: PRD025 | G3: =_xlfn.XLOOKUP(Sales_Transactions!$F3,Products!$A$2:$A$151,Products!$B$2:$B$151,"missing product") -> Nescafe Soft Drinks Pack | H3: =_xlfn.XLOOKUP(Sales_Transactions!$F3,Table9[Product_ID],Table9[Category],"Missing Catogory") -> Beverages | I3: STR094 | J3: =_xlfn.XLOOKUP(Sales_Transactions!$I3,Store!$A$2:$A$181,Store!$B$2:$B$181,"Missing Store") -> FreshMart Mumbai Central | K3: =_xlfn.XLOOKUP(Sales_Transactions!$I3,Store!$A$2:$A$181,Store!$D$2:$D$181,"East") -> West | L3: EMP0347 | M3: Dhanush Chandran | N3: =_xlfn.XLOOKUP(Sales_Transactions!$L3,Table12[Employee_ID],Table12[Department],"Missing Department") -> Sales | O3: 4 | P3: 383.51 | Q3: 0 | R3: 0 | S3: 1534.04 | T3: 1143.6 | U3: 390.44 | V3: Debit Card | W3: Not Returned | X3: In-Store | Y3: 11:14 | Z3: Weekday
A4: INV101198 | B4: 46054 | C4: CUST0422 | D4: =_xlfn.XLOOKUP(Sales_Transactions!$C4,Customer!$A$2:$A$701,Customer!$B$2:$B$701,"Missing") -> Balamurugan Naidu | E4: =_xlfn.XLOOKUP(Table14[[#This Row],[Customer_ID]],Table10[Customer_ID],Table10[Membership],"Missing Membership") -> Silver | F4: PRD074 | G4: =_xlfn.XLOOKUP(Sales_Transactions!$F4,Products!$A$2:$A$151,Products!$B$2:$B$151,"missing product") -> Surf Excel Tissue Combo | H4: =_xlfn.XLOOKUP(Sales_Transactions!$F4,Table9[Product_ID],Table9[Category],"Missing Catogory") -> Household | I4: STR024 | J4: =_xlfn.XLOOKUP(Sales_Transactions!$I4,Store!$A$2:$A$181,Store!$B$2:$B$181,"Missing Store") -> FreshMart Bengaluru Plaza | K4: =_xlfn.XLOOKUP(Sales_Transactions!$I4,Store!$A$2:$A$181,Store!$D$2:$D$181,"East") -> South | L4: EMP0005 | M4: Harini Sekar | N4: =_xlfn.XLOOKUP(Sales_Transactions!$L4,Table12[Employee_ID],Table12[Department],"Missing Department") -> Inventory | O4: 1 | P4: 414.29 | Q4: 0 | R4: 0 | S4: 476.43 | T4: 314.26 | U4: 162.17 | V4: Debit Card | W4: Not Returned | X4: In-Store | Y4: 20:21 | Z4: Weekend
A5: INV101268 | B5: 45885 | C5: CUST0689 | D5: =_xlfn.XLOOKUP(Sales_Transactions!$C5,Customer!$A$2:$A$701,Customer!$B$2:$B$701,"Missing") -> Karthik Pillai | E5: =_xlfn.XLOOKUP(Table14[[#This Row],[Customer_ID]],Table10[Customer_ID],Table10[Membership],"Missing Membership") -> Silver | F5: PRD111 | G5: =_xlfn.XLOOKUP(Sales_Transactions!$F5,Products!$A$2:$A$151,Products!$B$2:$B$151,"missing product") -> Aachi Idli Rice 500g | H5: =_xlfn.XLOOKUP(Sales_Transactions!$F5,Table9[Product_ID],Table9[Category],"Missing Catogory") -> Rice | I5: STR154 | J5: =_xlfn.XLOOKUP(Sales_Transactions!$I5,Store!$A$2:$A$181,Store!$B$2:$B$181,"Missing Store") -> FreshMart Lucknow Heights | K5: =_xlfn.XLOOKUP(Sales_Transactions!$I5,Store!$A$2:$A$181,Store!$D$2:$D$181,"East") -> North | L5: EMP0182 | M5: Arun Naicker | N5: =_xlfn.XLOOKUP(Sales_Transactions!$L5,Table12[Employee_ID],Table12[Department],"Missing Department") -> Operations | O5: 5 | P5: 225.45 | Q5: 0 | R5: 0 | S5: 1296.34 | T5: 954.5 | U5: 341.84 | V5: Debit Card | W5: Not Returned | X5: Mobile App | Y5: 20:32 | Z5: Weekend
A6: INV100071 | B6: 45918 | C6: CUST0475 | D6: =_xlfn.XLOOKUP(Sales_Transactions!$C6,Customer!$A$2:$A$701,Customer!$B$2:$B$701,"Missing") -> Gopal Prabhu | E6: =_xlfn.XLOOKUP(Table14[[#This Row],[Customer_ID]],Table10[Customer_ID],Table10[Membership],"Missing Membership") -> Gold | F6: PRD093 | G6: =_xlfn.XLOOKUP(Sales_Transactions!$F6,Products!$A$2:$A$151,Products!$B$2:$B$151,"missing product") -> Local Farm Fresh Vegetables 250ml | H6: =_xlfn.XLOOKUP(Sales_Transactions!$F6,Table9[Product_ID],Table9[Category],"Missing Catogory") -> Vegetables | I6: STR076 | J6: =_xlfn.XLOOKUP(Sales_Transactions!$I6,Store!$A$2:$A$181,Store!$B$2:$B$181,"Missing Store") -> FreshMart Hyderabad Towers | K6: =_xlfn.XLOOKUP(Sales_Transactions!$I6,Store!$A$2:$A$181,Store!$D$2:$D$181,"East") -> South | L6: EMP0099 | M6: Elango Nair | N6: =_xlfn.XLOOKUP(Sales_Transactions!$L6,Table12[Employee_ID],Table12[Department],"Missing Department") -> Cashier | O6: 3 | P6: 97.24 | Q6: 0 | R6: 0 | S6: 291.72 | T6: 239.46 | U6: 52.26 | V6: Net Banking | W6: Not Returned | X6: In-Store | Y6: 16:02 | Z6: Weekday
A7: INV100478 | B7: 46011 | C7: CUST0485 | D7: =_xlfn.XLOOKUP(Sales_Transactions!$C7,Customer!$A$2:$A$701,Customer!$B$2:$B$701,"Missing") -> Dhanush Venkataraman | E7: =_xlfn.XLOOKUP(Table14[[#This Row],[Customer_ID]],Table10[Customer_ID],Table10[Membership],"Missing Membership") -> Gold | F7: PRD057 | G7: =_xlfn.XLOOKUP(Sales_Transactions!$F7,Products!$A$2:$A$151,Products!$B$2:$B$151,"missing product") -> Parle Chocolates 500g | H7: =_xlfn.XLOOKUP(Sales_Transactions!$F7,Table9[Product_ID],Table9[Category],"Missing Catogory") -> Snacks | I7: STR071 | J7: =_xlfn.XLOOKUP(Sales_Transactions!$I7,Store!$A$2:$A$181,Store!$B$2:$B$181,"Missing Store") -> FreshMart Salem Crossing | K7: =_xlfn.XLOOKUP(Sales_Transactions!$I7,Store!$A$2:$A$181,Store!$D$2:$D$181,"East") -> South | L7: EMP0144 | M7: Chitra Nair | N7: =_xlfn.XLOOKUP(Sales_Transactions!$L7,Table12[Employee_ID],Table12[Department],"Missing Department") -> Cashier | O7: 8 | P7: 323.91 | Q7: 0 | R7: 0 | S7: 2979.97 | T7: 1880.4 | U7: 1099.57 | V7: Wallet | W7: Not Returned | X7: In-Store | Y7: 09:38 | Z7: Weekend
A8: INV101553 | B8: 45984 | C8: CUST0143 | D8: =_xlfn.XLOOKUP(Sales_Transactions!$C8,Customer!$A$2:$A$701,Customer!$B$2:$B$701,"Missing") -> Charulatha Iyer | E8: =_xlfn.XLOOKUP(Table14[[#This Row],[Customer_ID]],Table10[Customer_ID],Table10[Membership],"Missing Membership") -> Silver | F8: PRD070 | G8: =_xlfn.XLOOKUP(Sales_Transactions!$F8,Products!$A$2:$A$151,Products!$B$2:$B$151,"missing product") -> Surf Excel Batteries 2kg | H8: =_xlfn.XLOOKUP(Sales_Transactions!$F8,Table9[Product_ID],Table9[Category],"Missing Catogory") -> Household | I8: STR128 | J8: =_xlfn.XLOOKUP(Sales_Transactions!$I8,Store!$A$2:$A$181,Store!$B$2:$B$181,"Missing Store") -> FreshMart Surat Junction | K8: =_xlfn.XLOOKUP(Sales_Transactions!$I8,Store!$A$2:$A$181,Store!$D$2:$D$181,"East") -> West | L8: EMP0177 | M8: Raghav Iyer | N8: =_xlfn.XLOOKUP(Sales_Transactions!$L8,Table12[Employee_ID],Table12[Department],"Missing Department") -> Store Manager | O8: 2 | P8: 233.47 | Q8: 15 | R8: 70.04 | S8: 456.43 | T8: 377.96 | U8: 78.47 | V8: Wallet | W8: Not Returned | X8: Mobile App | Y8: 21:04 | Z8: Weekend
A9: INV101964 | B9: 45991 | C9: CUST0427 | D9: =_xlfn.XLOOKUP(Sales_Transactions!$C9,Customer!$A$2:$A$701,Customer!$B$2:$B$701,"Missing") -> Ashok Gounder | E9: =_xlfn.XLOOKUP(Table14[[#This Row],[Customer_ID]],Table10[Customer_ID],Table10[Membership],"Missing Membership") -> Bronze | F9: PRD097 | G9: =_xlfn.XLOOKUP(Sales_Transactions!$F9,Products!$A$2:$A$151,Products!$B$2:$B$151,"missing product") -> Local Farm Fresh Vegetables 250ml v2 | H9: =_xlfn.XLOOKUP(Sales_Transactions!$F9,Table9[Product_ID],Table9[Category],"Missing Catogory") -> Vegetables | I9: STR062 | J9: =_xlfn.XLOOKUP(Sales_Transactions!$I9,Store!$A$2:$A$181,Store!$B$2:$B$181,"Missing Store") -> FreshMart Hyderabad Crossing | K9: =_xlfn.XLOOKUP(Sales_Transactions!$I9,Store!$A$2:$A$181,Store!$D$2:$D$181,"East") -> South | L9: EMP0350 | M9: Uma Pandian | N9: =_xlfn.XLOOKUP(Sales_Transactions!$L9,Table12[Employee_ID],Table12[Department],"Missing Department") -> Cashier | O9: 4 | P9: 365.92 | Q9: 15 | R9: 219.55 | S9: 1430.75 | T9: 1241.52 | U9: 189.23 | V9: Wallet | W9: Not Returned | X9: In-Store | Y9: 19:16 | Z9: Weekend
A10: INV100003 | B10: 45920 | C10: CUST0438 | D10: =_xlfn.XLOOKUP(Sales_Transactions!$C10,Customer!$A$2:$A$701,Customer!$B$2:$B$701,"Missing") -> Nandhini Mudaliar | E10: =_xlfn.XLOOKUP(Table14[[#This Row],[Customer_ID]],Table10[Customer_ID],Table10[Membership],"Missing Membership") -> Bronze | F10: PRD119 | G10: =_xlfn.XLOOKUP(Sales_Transactions!$F10,Products!$A$2:$A$151,Products!$B$2:$B$151,"missing product") -> Gold Winner Sunflower Oil 200g | H10: =_xlfn.XLOOKUP(Sales_Transactions!$F10,Table9[Product_ID],Table9[Category],"Missing Catogory") -> Oil | I10: STR008 | J10: =_xlfn.XLOOKUP(Sales_Transactions!$I10,Store!$A$2:$A$181,Store!$B$2:$B$181,"Missing Store") -> FreshMart Kochi Plaza | K10: =_xlfn.XLOOKUP(Sales_Transactions!$I10,Store!$A$2:$A$181,Store!$D$2:$D$181,"East") -> South | L10: EMP0249 | M10: Radha Murugan | N10: =_xlfn.XLOOKUP(Sales_Transactions!$L10,Table12[Employee_ID],Table12[Department],"Missing Department") -> Inventory | O10: 1 | P10: 234.86 | Q10: 10 | R10: 23.49 | S10: 243.08 | T10: 213.23 | U10: 29.85 | V10: Cash | W10: Not Returned | X10: In-Store | Y10: 09:53 | Z10: Weekend
A11: INV100008 | B11: 46110 | C11: CUST0267 | D11: =_xlfn.XLOOKUP(Sales_Transactions!$C11,Customer!$A$2:$A$701,Customer!$B$2:$B$701,"Missing") -> Manoj Gounder | E11: =_xlfn.XLOOKUP(Table14[[#This Row],[Customer_ID]],Table10[Customer_ID],Table10[Membership],"Missing Membership") -> Silver | F11: PRD030 | G11: =_xlfn.XLOOKUP(Sales_Transactions!$F11,Products!$A$2:$A$151,Products!$B$2:$B$151,"missing product") -> Nescafe Tea Combo | H11: =_xlfn.XLOOKUP(Sales_Transactions!$F11,Table9[Product_ID],Table9[Category],"Missing Catogory") -> Beverages | I11: STR019 | J11: =_xlfn.XLOOKUP(Sales_Transactions!$I11,Store!$A$2:$A$181,Store!$B$2:$B$181,"Missing Store") -> FreshMart Hyderabad Heights | K11: =_xlfn.XLOOKUP(Sales_Transactions!$I11,Store!$A$2:$A$181,Store!$D$2:$D$181,"East") -> South | L11: EMP0273 | M11: Prasath Subramaniam | N11: =_xlfn.XLOOKUP(Sales_Transactions!$L11,Table12[Employee_ID],Table12[Department],"Missing Department") -> Store Manager | O11: 4 | P11: 172.63 | Q11: 0 | R11: 0 | S11: 794.1 | T11: 568 | U11: 226.1 | V11: Cash | W11: Not Returned | X11: In-Store | Y11: 17:13 | Z11: Weekend
A12: INV100017 | B12: 45792 | C12: CUST0680 | D12: =_xlfn.XLOOKUP(Sales_Transactions!$C12,Customer!$A$2:$A$701,Customer!$B$2:$B$701,"Missing") -> Lokesh Chandran | E12: =_xlfn.XLOOKUP(Table14[[#This Row],[Customer_ID]],Table10[Customer_ID],Table10[Membership],"Missing Membership") -> Silver | F12: PRD022 | G12: =_xlfn.XLOOKUP(Sales_Transactions!$F12,Products!$A$2:$A$151,Products!$B$2:$B$151,"missing product") -> Aavin Milk Pack | H12: =_xlfn.XLOOKUP(Sales_Transactions!$F12,Table9[Product_ID],Table9[Category],"Missing Catogory") -> Dairy | I12: STR075 | J12: =_xlfn.XLOOKUP(Sales_Transactions!$I12,Store!$A$2:$A$181,Store!$B$2:$B$181,"Missing Store") -> FreshMart Salem Main Road | K12: =_xlfn.XLOOKUP(Sales_Transactions!$I12,Store!$A$2:$A$181,Store!$D$2:$D$181,"East") -> South | L12: EMP0300 | M12: Thiru Raj | N12: =_xlfn.XLOOKUP(Sales_Transactions!$L12,Table12[Employee_ID],Table12[Department],"Missing Department") -> Sales | O12: 4 | P12: 397.22 | Q12: 20 | R12: 317.78 | S12: 1271.1 | T12: 1277.48 | U12: -6.38 | V12: Cash | W12: Not Returned | X12: In-Store | Y12: 17:19 | Z12: Weekday
A13: INV100021 | B13: 45803 | C13: CUST0589 | D13: =_xlfn.XLOOKUP(Sales_Transactions!$C13,Customer!$A$2:$A$701,Customer!$B$2:$B$701,"Missing") -> Ovi Venkataraman | E13: =_xlfn.XLOOKUP(Table14[[#This Row],[Customer_ID]],Table10[Customer_ID],Table10[Membership],"Missing Membership") -> Silver | F13: PRD029 | G13: =_xlfn.XLOOKUP(Sales_Transactions!$F13,Products!$A$2:$A$151,Products!$B$2:$B$151,"missing product") -> Pepsi Tea 200g | H13: =_xlfn.XLOOKUP(Sales_Transactions!$F13,Table9[Product_ID],Table9[Category],"Missing Catogory") -> Beverages | I13: STR053 | J13: =_xlfn.XLOOKUP(Sales_Transactions!$I13,Store!$A$2:$A$181,Store!$B$2:$B$181,"Missing Store") -> FreshMart Tiruppur Heights | K13: =_xlfn.XLOOKUP(Sales_Transactions!$I13,Store!$A$2:$A$181,Store!$D$2:$D$181,"East") -> South | L13: EMP0007 | M13: Udhay Selvam | N13: =_xlfn.XLOOKUP(Sales_Transactions!$L13,Table12[Employee_ID],Table12[Department],"Missing Department") -> Billing | O13: 5 | P13: 332.73 | Q13: 15 | R13: 249.55 | S13: 1414.1 | T13: 1306.1 | U13: 108 | V13: Cash | W13: Not Returned | X13: In-Store | Y13: 15:38 | Z13: Weekday
... A256: INV101632 | B256: 45914 | C256: CUST0060 | D256: =_xlfn.XLOOKUP(Sales_Transactions!$C256,Customer!$A$2:$A$701,Customer!$B$2:$B$701,"Missing") -> Anand Subramaniam | E256: =_xlfn.XLOOKUP(Table14[[#This Row],[Customer_ID]],Table10[Customer_ID],Table10[Membership],"Missing Membership") -> Gold | F256: PRD046 | G256: =_xlfn.XLOOKUP(Sales_Transactions!$F256,Products!$A$2:$A$151,Products!$B$2:$B$151,"missing product") -> ITC Ice Cream 250ml | H256: =_xlfn.XLOOKUP(Sales_Transactions!$F256,Table9[Product_ID],Table9[Category],"Missing Catogory") -> Frozen Foods | I256: STR033 | J256: =_xlfn.XLOOKUP(Sales_Transactions!$I256,Store!$A$2:$A$181,Store!$B$2:$B$181,"Missing Store") -> FreshMart Ahmedabad Complex | K256: =_xlfn.XLOOKUP(Sales_Transactions!$I256,Store!$A$2:$A$181,Store!$D$2:$D$181,"East") -> South | L256: EMP0113 | M256: Radha Rao | N256: =_xlfn.XLOOKUP(Sales_Transactions!$L256,Table12[Employee_ID],Table12[Department],"Missing Department") -> Inventory | O256: 7 | P256: 58.27 | Q256: 10 | R256: 40.79 | S256: 422.17 | T256: 339.01 | U256: 83.16 | V256: Cash | W256: Not Returned | X256: In-Store | Y256: 15:45 | Z256: Weekend
A257: INV101634 | B257: 45942 | C257: CUST0353 | D257: =_xlfn.XLOOKUP(Sales_Transactions!$C257,Customer!$A$2:$A$701,Customer!$B$2:$B$701,"Missing") -> Mala Nair | E257: =_xlfn.XLOOKUP(Table14[[#This Row],[Customer_ID]],Table10[Customer_ID],Table10[Membership],"Missing Membership") -> Gold | F257: PRD001 | G257: =_xlfn.XLOOKUP(Sales_Transactions!$F257,Products!$A$2:$A$151,Products!$B$2:$B$151,"missing product") -> Local Bakers Buns 1kg | H257: =_xlfn.XLOOKUP(Sales_Transactions!$F257,Table9[Product_ID],Table9[Category],"Missing Catogory") -> Bakery | I257: STR145 | J257: =_xlfn.XLOOKUP(Sales_Transactions!$I257,Store!$A$2:$A$181,Store!$B$2:$B$181,"Missing Store") -> FreshMart Lucknow Main Road | K257: =_xlfn.XLOOKUP(Sales_Transactions!$I257,Store!$A$2:$A$181,Store!$D$2:$D$181,"East") -> North | L257: EMP0117 | M257: Janani Krishnan | N257: =_xlfn.XLOOKUP(Sales_Transactions!$L257,Table12[Employee_ID],Table12[Department],"Missing Department") -> Billing | O257: 5 | P257: 340.64 | Q257: 0 | R257: 0 | S257: Rs.1958.68 | T257: 923.7 | U257: 1034.98 | V257: Cash | W257: Not Returned | X257: In-Store | Y257: 13:37 | Z257: Weekend
A258: INV101636 | B258: 45886 | C258: CUST0156 | D258: =_xlfn.XLOOKUP(Sales_Transactions!$C258,Customer!$A$2:$A$701,Customer!$B$2:$B$701,"Missing") -> Tara Chettiar | E258: =_xlfn.XLOOKUP(Table14[[#This Row],[Customer_ID]],Table10[Customer_ID],Table10[Membership],"Missing Membership") -> Gold | F258: PRD142 | G258: =_xlfn.XLOOKUP(Sales_Transactions!$F258,Products!$A$2:$A$151,Products!$B$2:$B$151,"missing product") -> Lizol Dishwash 200g | H258: =_xlfn.XLOOKUP(Sales_Transactions!$F258,Table9[Product_ID],Table9[Category],"Missing Catogory") -> Cleaning | I258: STR022 | J258: =_xlfn.XLOOKUP(Sales_Transactions!$I258,Store!$A$2:$A$181,Store!$B$2:$B$181,"Missing Store") -> FreshMart Tiruppur Complex | K258: =_xlfn.XLOOKUP(Sales_Transactions!$I258,Store!$A$2:$A$181,Store!$D$2:$D$181,"East") -> South | L258: EMP0284 | M258: Naveen Venkataraman | N258: =_xlfn.XLOOKUP(Sales_Transactions!$L258,Table12[Employee_ID],Table12[Department],"Missing Department") -> Sales | O258: 3 | P258: 568.76 | Q258: 0 | R258: 0 | S258: 1962.22 | T258: 1187.61 | U258: 774.61 | V258: Cash | W258: Not Returned | X258: In-Store | Y258: 09:41 | Z258: Weekend
A259: INV101643 | B259: 45952 | C259: CUST0534 | D259: =_xlfn.XLOOKUP(Sales_Transactions!$C259,Customer!$A$2:$A$701,Customer!$B$2:$B$701,"Missing") -> Kalpana Nair | E259: =_xlfn.XLOOKUP(Table14[[#This Row],[Customer_ID]],Table10[Customer_ID],Table10[Membership],"Missing Membership") -> Silver | F259: PRD025 | G259: =_xlfn.XLOOKUP(Sales_Transactions!$F259,Products!$A$2:$A$151,Products!$B$2:$B$151,"missing product") -> Nescafe Soft Drinks Pack | H259: =_xlfn.XLOOKUP(Sales_Transactions!$F259,Table9[Product_ID],Table9[Category],"Missing Catogory") -> Beverages | I259: STR064 | J259: =_xlfn.XLOOKUP(Sales_Transactions!$I259,Store!$A$2:$A$181,Store!$B$2:$B$181,"Missing Store") -> FreshMart Kochi Extension | K259: =_xlfn.XLOOKUP(Sales_Transactions!$I259,Store!$A$2:$A$181,Store!$D$2:$D$181,"East") -> South | L259: EMP0234 | M259: Lalitha Menon | N259: =_xlfn.XLOOKUP(Sales_Transactions!$L259,Table12[Employee_ID],Table12[Department],"Missing Department") -> Sales | O259: 5 | P259: 383.51 | Q259: 0 | R259: 0 | S259: 1917.55 | T259: 1429.5 | U259: 488.05 | V259: Cash | W259: Not Returned | X259: Online | Y259: 18:26 | Z259: Weekday
A260: INV101657 | B260: 45834 | C260: CUST0346 | D260: =_xlfn.XLOOKUP(Sales_Transactions!$C260,Customer!$A$2:$A$701,Customer!$B$2:$B$701,"Missing") -> Thenmozhi Devi | E260: =_xlfn.XLOOKUP(Table14[[#This Row],[Customer_ID]],Table10[Customer_ID],Table10[Membership],"Missing Membership") -> Gold | F260: PRD051 | G260: =_xlfn.XLOOKUP(Sales_Transactions!$F260,Products!$A$2:$A$151,Products!$B$2:$B$151,"missing product") -> Cadbury Biscuits 250ml | H260: =_xlfn.XLOOKUP(Sales_Transactions!$F260,Table9[Product_ID],Table9[Category],"Missing Catogory") -> Snacks | I260: STR160 | J260: =_xlfn.XLOOKUP(Sales_Transactions!$I260,Store!$A$2:$A$181,Store!$B$2:$B$181,"Missing Store") -> FreshMart Lucknow Complex | K260: =_xlfn.XLOOKUP(Sales_Transactions!$I260,Store!$A$2:$A$181,Store!$D$2:$D$181,"East") -> North | L260: EMP0073 | M260: Harini Prabhu | N260: =_xlfn.XLOOKUP(Sales_Transactions!$L260,Table12[Employee_ID],Table12[Department],"Missing Department") -> Sales | O260: 6 | P260: 158.31 | Q260: 5 | R260: 47.49 | S260: 902.37 | T260: 676.8 | U260: 225.57 | V260: Cash | W260: Not Returned | X260: In-Store | Y260: 12:20 | Z260: Weekday
A261: INV101673 | B261: 45888 | C261: CUST0409 | D261: =_xlfn.XLOOKUP(Sales_Transactions!$C261,Customer!$A$2:$A$701,Customer!$B$2:$B$701,"Missing") -> Banu Subramaniam | E261: =_xlfn.XLOOKUP(Table14[[#This Row],[Customer_ID]],Table10[Customer_ID],Table10[Membership],"Missing Membership") -> Gold | F261: PRD032 | G261: =_xlfn.XLOOKUP(Sales_Transactions!$F261,Products!$A$2:$A$151,Products!$B$2:$B$151,"missing product") -> Coca-Cola Coffee Combo | H261: =_xlfn.XLOOKUP(Sales_Transactions!$F261,Table9[Product_ID],Table9[Category],"Missing Catogory") -> Beverages | I261: STR006 | J261: =_xlfn.XLOOKUP(Sales_Transactions!$I261,Store!$A$2:$A$181,Store!$B$2:$B$181,"Missing Store") -> FreshMart Mysuru Junction | K261: =_xlfn.XLOOKUP(Sales_Transactions!$I261,Store!$A$2:$A$181,Store!$D$2:$D$181,"East") -> South | L261: EMP0265 | M261: Padma Subramaniam | N261: =_xlfn.XLOOKUP(Sales_Transactions!$L261,Table12[Employee_ID],Table12[Department],"Missing Department") -> Operations | O261: 8 | P261: 154.01 | Q261: 0 | R261: 0 | S261: 1232.08 | T261: 927.28 | U261: 304.8 | V261: Cash | W261: Not Returned | X261: In-Store | Y261: 16:05 | Z261: Weekday
A262: INV101688 | B262: 45788 | C262: CUST0239 | D262: =_xlfn.XLOOKUP(Sales_Transactions!$C262,Customer!$A$2:$A$701,Customer!$B$2:$B$701,"Missing") -> Jayakumar Velan | E262: =_xlfn.XLOOKUP(Table14[[#This Row],[Customer_ID]],Table10[Customer_ID],Table10[Membership],"Missing Membership") -> Silver | F262: PRD060 | G262: =_xlfn.XLOOKUP(Sales_Transactions!$F262,Products!$A$2:$A$151,Products!$B$2:$B$151,"missing product") -> Himalaya Soap 250ml | H262: =_xlfn.XLOOKUP(Sales_Transactions!$F262,Table9[Product_ID],Table9[Category],"Missing Catogory") -> Personal Care | I262: STR149 | J262: =_xlfn.XLOOKUP(Sales_Transactions!$I262,Store!$A$2:$A$181,Store!$B$2:$B$181,"Missing Store") -> FreshMart Jaipur Point | K262: =_xlfn.XLOOKUP(Sales_Transactions!$I262,Store!$A$2:$A$181,Store!$D$2:$D$181,"East") -> North | L262: EMP0246 | M262: Padma Chettiar | N262: =_xlfn.XLOOKUP(Sales_Transactions!$L262,Table12[Employee_ID],Table12[Department],"Missing Department") -> Sales | O262: 1 | P262: 72.93 | Q262: 0 | R262: 0 | S262: 83.87 | T262: 54.25 | U262: 29.62 | V262: Cash | W262: Not Returned | X262: In-Store | Y262: 09:03 | Z262: Weekend
A263: INV101689 | B263: 45824 | C263: CUST0346 | D263: =_xlfn.XLOOKUP(Sales_Transactions!$C263,Customer!$A$2:$A$701,Customer!$B$2:$B$701,"Missing") -> Thenmozhi Devi | E263: =_xlfn.XLOOKUP(Table14[[#This Row],[Customer_ID]],Table10[Customer_ID],Table10[Membership],"Missing Membership") -> Gold | F263: PRD006 | G263: =_xlfn.XLOOKUP(Sales_Transactions!$F263,Products!$A$2:$A$151,Products!$B$2:$B$151,"missing product") -> Harvest Gold Cookies 500g | H263: =_xlfn.XLOOKUP(Sales_Transactions!$F263,Table9[Product_ID],Table9[Category],"Missing Catogory") -> Bakery | I263: STR106 | J263: =_xlfn.XLOOKUP(Sales_Transactions!$I263,Store!$A$2:$A$181,Store!$B$2:$B$181,"Missing Store") -> FreshMart Ahmedabad Crossing | K263: =_xlfn.XLOOKUP(Sales_Transactions!$I263,Store!$A$2:$A$181,Store!$D$2:$D$181,"East") -> West | L263: EMP0347 | M263: Dhanush Chandran | N263: =_xlfn.XLOOKUP(Sales_Transactions!$L263,Table12[Employee_ID],Table12[Department],"Missing Department") -> Sales | O263: 5 | P263: 345.01 | Q263: 0 | R263: 0 | S263: 1725.05 | T263: 1081.6 | U263: 643.45 | V263: Cash | W263: Not Returned | X263: In-Store | Y263: 19:18 | Z263: Weekday
A264: INV101690 | B264: 45923 | C264: CUST0011 | D264: =_xlfn.XLOOKUP(Sales_Transactions!$C264,Customer!$A$2:$A$701,Customer!$B$2:$B$701,"Missing") -> Prasath Mudaliar | E264: =_xlfn.XLOOKUP(Table14[[#This Row],[Customer_ID]],Table10[Customer_ID],Table10[Membership],"Missing Membership") -> Bronze | F264: PRD131 | G264: =_xlfn.XLOOKUP(Sales_Transactions!$F264,Products!$A$2:$A$151,Products!$B$2:$B$151,"missing product") -> Sakthi Powdered Spices 250ml | H264: =_xlfn.XLOOKUP(Sales_Transactions!$F264,Table9[Product_ID],Table9[Category],"Missing Catogory") -> Masala | I264: STR046 | J264: =_xlfn.XLOOKUP(Sales_Transactions!$I264,Store!$A$2:$A$181,Store!$B$2:$B$181,"Missing Store") -> FreshMart Mysuru Colony | K264: =_xlfn.XLOOKUP(Sales_Transactions!$I264,Store!$A$2:$A$181,Store!$D$2:$D$181,"East") -> South | L264: EMP0087 | M264: Nagarajan Rao | N264: =_xlfn.XLOOKUP(Sales_Transactions!$L264,Table12[Employee_ID],Table12[Department],"Missing Department") -> Sales | O264: 2 | P264: 93.47 | Q264: 0 | R264: 0 | S264: 186.94 | T264: 144.58 | U264: 42.36 | V264: Cash | W264: Returned | X264: In-Store | Y264: 18:57 | Z264: Weekday
A265: INV101709 | B265: 46059 | C265: CUST0399 | D265: =_xlfn.XLOOKUP(Sales_Transactions!$C265,Customer!$A$2:$A$701,Customer!$B$2:$B$701,"Missing") -> Karthik Kumar | E265: =_xlfn.XLOOKUP(Table14[[#This Row],[Customer_ID]],Table10[Customer_ID],Table10[Membership],"Missing Membership") -> Silver | F265: PRD082 | G265: =_xlfn.XLOOKUP(Sales_Transactions!$F265,Products!$A$2:$A$151,Products!$B$2:$B$151,"missing product") -> Organic Fresh Fresh Fruits Pack | H265: =_xlfn.XLOOKUP(Sales_Transactions!$F265,Table9[Product_ID],Table9[Category],"Missing Catogory") -> Fruits | I265: STR145 | J265: =_xlfn.XLOOKUP(Sales_Transactions!$I265,Store!$A$2:$A$181,Store!$B$2:$B$181,"Missing Store") -> FreshMart Lucknow Main Road | K265: =_xlfn.XLOOKUP(Sales_Transactions!$I265,Store!$A$2:$A$181,Store!$D$2:$D$181,"East") -> North | L265: EMP0002 | M265: Lokesh Gounder | N265: =_xlfn.XLOOKUP(Sales_Transactions!$L265,Table12[Employee_ID],Table12[Department],"Missing Department") -> Billing | O265: 3 | P265: 232.92 | Q265: 15 | R265: 104.81 | S265: 593.95 | T265: 577.23 | U265: 16.72 | V265: Cash | W265: Not Returned | X265: In-Store | Y265: 13:24 | Z265: Weekday
A266: INV101713 | B266: 45895 | C266: CUST0495 | D266: =_xlfn.XLOOKUP(Sales_Transactions!$C266,Customer!$A$2:$A$701,Customer!$B$2:$B$701,"Missing") -> Bhuvana Pillai | E266: =_xlfn.XLOOKUP(Table14[[#This Row],[Customer_ID]],Table10[Customer_ID],Table10[Membership],"Missing Membership") -> Gold | F266: PRD012 | G266: =_xlfn.XLOOKUP(Sales_Transactions!$F266,Products!$A$2:$A$151,Products!$B$2:$B$151,"missing product") -> Harvest Gold Rusk 1kg | H266: =_xlfn.XLOOKUP(Sales_Transactions!$F266,Table9[Product_ID],Table9[Category],"Missing Catogory") -> Bakery | I266: STR083 | J266: =_xlfn.XLOOKUP(Sales_Transactions!$I266,Store!$A$2:$A$181,Store!$B$2:$B$181,"Missing Store") -> FreshMart Salem Colony | K266: =_xlfn.XLOOKUP(Sales_Transactions!$I266,Store!$A$2:$A$181,Store!$D$2:$D$181,"East") -> South | L266: EMP0074 | M266: Indira Varma | N266: =_xlfn.XLOOKUP(Sales_Transactions!$L266,Table12[Employee_ID],Table12[Department],"Missing Department") -> Sales | O266: 8 | P266: 599.45 | Q266: 5 | R266: 239.78 | S266: Rs.4555.82 | T266: 2691.2 | U266: 1864.62 | V266: Cash | W266: Not Returned | X266: In-Store | Y266: 11:18 | Z266: Weekday
A267: INV101725 | B267: 45759 | C267: CUST0324 | D267: =_xlfn.XLOOKUP(Sales_Transactions!$C267,Customer!$A$2:$A$701,Customer!$B$2:$B$701,"Missing") -> Tamil Velan | E267: =_xlfn.XLOOKUP(Table14[[#This Row],[Customer_ID]],Table10[Customer_ID],Table10[Membership],"Missing Membership") -> Gold | F267: PRD006 | G267: =_xlfn.XLOOKUP(Sales_Transactions!$F267,Products!$A$2:$A$151,Products!$B$2:$B$151,"missing product") -> Harvest Gold Cookies 500g | H267: =_xlfn.XLOOKUP(Sales_Transactions!$F267,Table9[Product_ID],Table9[Category],"Missing Catogory") -> Bakery | I267: STR003 | J267: =_xlfn.XLOOKUP(Sales_Transactions!$I267,Store!$A$2:$A$181,Store!$B$2:$B$181,"Missing Store") -> FreshMart Tiruppur Square | K267: =_xlfn.XLOOKUP(Sales_Transactions!$I267,Store!$A$2:$A$181,Store!$D$2:$D$181,"East") -> South | L267: EMP0298 | M267: Balaji Reddy | N267: =_xlfn.XLOOKUP(Sales_Transactions!$L267,Table12[Employee_ID],Table12[Department],"Missing Department") -> Billing | O267: 8 | P267: 373.66 | Q267: 0 | R267: 0 | S267: 3437.67 | T267: 1730.56 | U267: 1707.11 | V267: Cash | W267: Not Returned | X267: Online | Y267: 12:47 | Z267: Weekend
A268: INV101732 | B268: 46040 | C268: CUST0569 | D268: =_xlfn.XLOOKUP(Sales_Transactions!$C268,Customer!$A$2:$A$701,Customer!$B$2:$B$701,"Missing") -> Sathish Krishnan | E268: =_xlfn.XLOOKUP(Table14[[#This Row],[Customer_ID]],Table10[Customer_ID],Table10[Membership],"Missing Membership") -> Bronze | F268: PRD024 | G268: =_xlfn.XLOOKUP(Sales_Transactions!$F268,Products!$A$2:$A$151,Products!$B$2:$B$151,"missing product") -> Aavin Milk Pack v2 | H268: =_xlfn.XLOOKUP(Sales_Transactions!$F268,Table9[Product_ID],Table9[Category],"Missing Catogory") -> Dairy | I268: STR151 | J268: =_xlfn.XLOOKUP(Sales_Transactions!$I268,Store!$A$2:$A$181,Store!$B$2:$B$181,"Missing Store") -> FreshMart Chandigarh Square | K268: =_xlfn.XLOOKUP(Sales_Transactions!$I268,Store!$A$2:$A$181,Store!$D$2:$D$181,"East") -> North | L268: EMP0277 | M268: Arun Velan | N268: =_xlfn.XLOOKUP(Sales_Transactions!$L268,Table12[Employee_ID],Table12[Department],"Missing Department") -> Cashier | O268: 3 | P268: 313.47 | Q268: 0 | R268: 0 | S268: 1081.47 | T268: 738.36 | U268: 343.11 | V268: Cash | W268: Not Returned | X268: Mobile App | Y268: 09:14 | Z268: Weekend
A269: INV101739 | B269: 46087 | C269: CUST0324 | D269: =_xlfn.XLOOKUP(Sales_Transactions!$C269,Customer!$A$2:$A$701,Customer!$B$2:$B$701,"Missing") -> Tamil Velan | E269: =_xlfn.XLOOKUP(Table14[[#This Row],[Customer_ID]],Table10[Customer_ID],Table10[Membership],"Missing Membership") -> Gold | F269: PRD082 | G269: =_xlfn.XLOOKUP(Sales_Transactions!$F269,Products!$A$2:$A$151,Products!$B$2:$B$151,"missing product") -> Organic Fresh Fresh Fruits Pack | H269: =_xlfn.XLOOKUP(Sales_Transactions!$F269,Table9[Product_ID],Table9[Category],"Missing Catogory") -> Fruits | I269: STR054 | J269: =_xlfn.XLOOKUP(Sales_Transactions!$I269,Store!$A$2:$A$181,Store!$B$2:$B$181,"Missing Store") -> FreshMart Mysuru Plaza | K269: =_xlfn.XLOOKUP(Sales_Transactions!$I269,Store!$A$2:$A$181,Store!$D$2:$D$181,"East") -> South | L269: EMP0104 | M269: Pandi Nair | N269: =_xlfn.XLOOKUP(Sales_Transactions!$L269,Table12[Employee_ID],Table12[Department],"Missing Department") -> Inventory | O269: 3 | P269: 246.7 | Q269: 0 | R269: 0 | S269: 740.1 | T269: 577.23 | U269: 162.87 | V269: Cash | W269: Not Returned | X269: In-Store | Y269: 20:11 | Z269: Weekday
A270: INV101740 | B270: 45941 | C270: CUST0049 | D270: =_xlfn.XLOOKUP(Sales_Transactions!$C270,Customer!$A$2:$A$701,Customer!$B$2:$B$701,"Missing") -> Lokesh Gupta | E270: =_xlfn.XLOOKUP(Table14[[#This Row],[Customer_ID]],Table10[Customer_ID],Table10[Membership],"Missing Membership") -> Gold | F270: PRD026 | G270: =_xlfn.XLOOKUP(Sales_Transactions!$F270,Products!$A$2:$A$151,Products!$B$2:$B$151,"missing product") -> Nescafe Coffee 1kg | H270: =_xlfn.XLOOKUP(Sales_Transactions!$F270,Table9[Product_ID],Table9[Category],"Missing Catogory") -> Beverages | I270: STR107 | J270: =_xlfn.XLOOKUP(Sales_Transactions!$I270,Store!$A$2:$A$181,Store!$B$2:$B$181,"Missing Store") -> FreshMart Surat Arcade | K270: =_xlfn.XLOOKUP(Sales_Transactions!$I270,Store!$A$2:$A$181,Store!$D$2:$D$181,"East") -> West | L270: EMP0038 | M270: Yamuna Achari | N270: =_xlfn.XLOOKUP(Sales_Transactions!$L270,Table12[Employee_ID],Table12[Department],"Missing Department") -> Inventory | O270: 4 | P270: 332.66 | Q270: 0 | R270: 0 | S270: 1530.24 | T270: 989 | U270: 541.24 | V270: Cash | W270: Not Returned | X270: In-Store | Y270: 16:40 | Z270: Weekend
A271: INV101741 | B271: 45764 | C271: CUST0123 | D271: =_xlfn.XLOOKUP(Sales_Transactions!$C271,Customer!$A$2:$A$701,Customer!$B$2:$B$701,"Missing") -> Sudha Rao | E271: =_xlfn.XLOOKUP(Table14[[#This Row],[Customer_ID]],Table10[Customer_ID],Table10[Membership],"Missing Membership") -> Bronze | F271: PRD056 | G271: =_xlfn.XLOOKUP(Sales_Transactions!$F271,Products!$A$2:$A$151,Products!$B$2:$B$151,"missing product") -> Cadbury Namkeen Combo | H271: =_xlfn.XLOOKUP(Sales_Transactions!$F271,Table9[Product_ID],Table9[Category],"Missing Catogory") -> Snacks | I271: STR041 | J271: =_xlfn.XLOOKUP(Sales_Transactions!$I271,Store!$A$2:$A$181,Store!$B$2:$B$181,"Missing Store") -> FreshMart Tiruppur Colony | K271: =_xlfn.XLOOKUP(Sales_Transactions!$I271,Store!$A$2:$A$181,Store!$D$2:$D$181,"East") -> South | L271: EMP0325 | M271: Chandran Naidu | N271: =_xlfn.XLOOKUP(Sales_Transactions!$L271,Table12[Employee_ID],Table12[Department],"Missing Department") -> Cashier | O271: 2 | P271: 333.54 | Q271: 0 | R271: 0 | S271: 667.08 | T271: 476.86 | U271: 190.22 | V271: Cash | W271: Not Returned | X271: Online | Y271: 19:54 | Z271: Weekday
A272: INV101747 | B272: 45837 | C272: CUST0686 | D272: =_xlfn.XLOOKUP(Sales_Transactions!$C272,Customer!$A$2:$A$701,Customer!$B$2:$B$701,"Missing") -> Hemalatha Balan | E272: =_xlfn.XLOOKUP(Table14[[#This Row],[Customer_ID]],Table10[Customer_ID],Table10[Membership],"Missing Membership") -> Gold | F272: PRD037 | G272: =_xlfn.XLOOKUP(Sales_Transactions!$F272,Products!$A$2:$A$151,Products!$B$2:$B$151,"missing product") -> ITC Frozen Snacks 250ml | H272: =_xlfn.XLOOKUP(Sales_Transactions!$F272,Table9[Product_ID],Table9[Category],"Missing Catogory") -> Frozen Foods | I272: STR006 | J272: =_xlfn.XLOOKUP(Sales_Transactions!$I272,Store!$A$2:$A$181,Store!$B$2:$B$181,"Missing Store") -> FreshMart Mysuru Junction | K272: =_xlfn.XLOOKUP(Sales_Transactions!$I272,Store!$A$2:$A$181,Store!$D$2:$D$181,"East") -> South | L272: EMP0265 | M272: Padma Subramaniam | N272: =_xlfn.XLOOKUP(Sales_Transactions!$L272,Table12[Employee_ID],Table12[Department],"Missing Department") -> Operations | O272: 8 | P272: 271.36 | Q272: 10 | R272: 217.09 | S272: 2246.86 | T272: 1675.04 | U272: 571.82 | V272: Cash | W272: Not Returned | X272: In-Store | Y272: 13:37 | Z272: Weekend
A273: INV101751 | B273: 45923 | C273: Customer Id Missing | D273: =_xlfn.XLOOKUP(Sales_Transactions!$C273,Customer!$A$2:$A$701,Customer!$B$2:$B$701,"Missing") -> Missing | E273: =_xlfn.XLOOKUP(Table14[[#This Row],[Customer_ID]],Table10[Customer_ID],Table10[Membership],"Missing Membership") -> Missing Membership | F273: PRD142 | G273: =_xlfn.XLOOKUP(Sales_Transactions!$F273,Products!$A$2:$A$151,Products!$B$2:$B$151,"missing product") -> Lizol Dishwash 200g | H273: =_xlfn.XLOOKUP(Sales_Transactions!$F273,Table9[Product_ID],Table9[Category],"Missing Catogory") -> Cleaning | I273: STR053 | J273: =_xlfn.XLOOKUP(Sales_Transactions!$I273,Store!$A$2:$A$181,Store!$B$2:$B$181,"Missing Store") -> FreshMart Tiruppur Heights | K273: =_xlfn.XLOOKUP(Sales_Transactions!$I273,Store!$A$2:$A$181,Store!$D$2:$D$181,"East") -> South | L273: EMP0133 | M273: Deepak Naicker | N273: =_xlfn.XLOOKUP(Sales_Transactions!$L273,Table12[Employee_ID],Table12[Department],"Missing Department") -> Sales | O273: 1 | P273: 522.78 | Q273: 10 | R273: 52.28 | S273: 470.5 | T273: 395.87 | U273: 74.63 | V273: Cash | W273: Not Returned | X273: Online | Y273: 16:18 | Z273: Weekday
A274: INV101754 | B274: 46016 | C274: CUST0587 | D274: =_xlfn.XLOOKUP(Sales_Transactions!$C274,Customer!$A$2:$A$701,Customer!$B$2:$B$701,"Missing") -> Uma Iyer | E274: =_xlfn.XLOOKUP(Table14[[#This Row],[Customer_ID]],Table10[Customer_ID],Table10[Membership],"Missing Membership") -> Bronze | F274: PRD024 | G274: =_xlfn.XLOOKUP(Sales_Transactions!$F274,Products!$A$2:$A$151,Products!$B$2:$B$151,"missing product") -> Aavin Milk Pack v2 | H274: =_xlfn.XLOOKUP(Sales_Transactions!$F274,Table9[Product_ID],Table9[Category],"Missing Catogory") -> Dairy | I274: STR136 | J274: =_xlfn.XLOOKUP(Sales_Transactions!$I274,Store!$A$2:$A$181,Store!$B$2:$B$181,"Missing Store") -> FreshMart Nagpur Crossing | K274: =_xlfn.XLOOKUP(Sales_Transactions!$I274,Store!$A$2:$A$181,Store!$D$2:$D$181,"East") -> West | L274: EMP0070 | M274: Umesh Subramaniam | N274: =_xlfn.XLOOKUP(Sales_Transactions!$L274,Table12[Employee_ID],Table12[Department],"Missing Department") -> Sales | O274: 1 | P274: 313.47 | Q274: 5 | R274: 15.67 | S274: 297.8 | T274: 246.12 | U274: 51.68 | V274: Cash | W274: Not Returned | X274: In-Store | Y274: 19:32 | Z274: Weekday
A275: INV101755 | B275: 45788 | C275: CUST0682 | D275: =_xlfn.XLOOKUP(Sales_Transactions!$C275,Customer!$A$2:$A$701,Customer!$B$2:$B$701,"Missing") -> Gopal Krishnan | E275: =_xlfn.XLOOKUP(Table14[[#This Row],[Customer_ID]],Table10[Customer_ID],Table10[Membership],"Missing Membership") -> Silver | F275: PRD009 | G275: =_xlfn.XLOOKUP(Sales_Transactions!$F275,Products!$A$2:$A$151,Products!$B$2:$B$151,"missing product") -> Harvest Gold Buns 200g | H275: =_xlfn.XLOOKUP(Sales_Transactions!$F275,Table9[Product_ID],Table9[Category],"Missing Catogory") -> Bakery | I275: STR077 | J275: =_xlfn.XLOOKUP(Sales_Transactions!$I275,Store!$A$2:$A$181,Store!$B$2:$B$181,"Missing Store") -> FreshMart Kochi Gardens | K275: =_xlfn.XLOOKUP(Sales_Transactions!$I275,Store!$A$2:$A$181,Store!$D$2:$D$181,"East") -> South | L275: EMP0030 | M275: Hariharan Rao | N275: =_xlfn.XLOOKUP(Sales_Transactions!$L275,Table12[Employee_ID],Table12[Department],"Missing Department") -> Cashier | O275: 4 | P275: 661.91 | Q275: 20 | R275: 529.53 | S275: 2435.83 | T275: 1594.88 | U275: 840.95 | V275: Cash | W275: Not Returned | X275: Online | Y275: 18:39 | Z275: Weekend
A276: INV101756 | B276: 46019 | C276: CUST0341 | D276: =_xlfn.XLOOKUP(Sales_Transactions!$C276,Customer!$A$2:$A$701,Customer!$B$2:$B$701,"Missing") -> Elango Sekar | E276: =_xlfn.XLOOKUP(Table14[[#This Row],[Customer_ID]],Table10[Customer_ID],Table10[Membership],"Missing Membership") -> Silver | F276: PRD030 | G276: =_xlfn.XLOOKUP(Sales_Transactions!$F276,Products!$A$2:$A$151,Products!$B$2:$B$151,"missing product") -> Nescafe Tea Combo | H276: =_xlfn.XLOOKUP(Sales_Transactions!$F276,Table9[Product_ID],Table9[Category],"Missing Catogory") -> Beverages | I276: STR071 | J276: =_xlfn.XLOOKUP(Sales_Transactions!$I276,Store!$A$2:$A$181,Store!$B$2:$B$181,"Missing Store") -> FreshMart Salem Crossing | K276: =_xlfn.XLOOKUP(Sales_Transactions!$I276,Store!$A$2:$A$181,Store!$D$2:$D$181,"East") -> South | L276: EMP0144 | M276: Chitra Nair | N276: =_xlfn.XLOOKUP(Sales_Transactions!$L276,Table12[Employee_ID],Table12[Department],"Missing Department") -> Cashier | O276: 4 | P276: 172.63 | Q276: 0 | R276: 0 | S276: 794.1 | T276: 568 | U276: 226.1 | V276: Cash | W276: Not Returned | X276: In-Store | Y276: 15:58 | Z276: Weekend
A277: INV101763 | B277: 45905 | C277: CUST0071 | D277: =_xlfn.XLOOKUP(Sales_Transactions!$C277,Customer!$A$2:$A$701,Customer!$B$2:$B$701,"Missing") -> Venkat Iyer | E277: =_xlfn.XLOOKUP(Table14[[#This Row],[Customer_ID]],Table10[Customer_ID],Table10[Membership],"Missing Membership") -> Silver | F277: PRD008 | G277: =_xlfn.XLOOKUP(Sales_Transactions!$F277,Products!$A$2:$A$151,Products!$B$2:$B$151,"missing product") -> Britannia Cookies 200g | H277: =_xlfn.XLOOKUP(Sales_Transactions!$F277,Table9[Product_ID],Table9[Category],"Missing Catogory") -> Bakery | I277: STR172 | J277: =_xlfn.XLOOKUP(Sales_Transactions!$I277,Store!$A$2:$A$181,Store!$B$2:$B$181,"Missing Store") -> FreshMart Guwahati Heights | K277: =_xlfn.XLOOKUP(Sales_Transactions!$I277,Store!$A$2:$A$181,Store!$D$2:$D$181,"East") -> East | L277: EMP0081 | M277: Radha Selvam | N277: =_xlfn.XLOOKUP(Sales_Transactions!$L277,Table12[Employee_ID],Table12[Department],"Missing Department") -> Sales | O277: 5 | P277: 455.79 | Q277: 0 | R277: 0 | S277: 2278.95 | T277: 1414.4 | U277: 864.55 | V277: Cash | W277: Not Returned | X277: In-Store | Y277: 13:28 | Z277: Weekday
A278: INV101766 | B278: 45832 | C278: CUST0442 | D278: =_xlfn.XLOOKUP(Sales_Transactions!$C278,Customer!$A$2:$A$701,Customer!$B$2:$B$701,"Missing") -> Kamala Rao | E278: =_xlfn.XLOOKUP(Table14[[#This Row],[Customer_ID]],Table10[Customer_ID],Table10[Membership],"Missing Membership") -> Silver | F278: PRD055 | G278: =_xlfn.XLOOKUP(Sales_Transactions!$F278,Products!$A$2:$A$151,Products!$B$2:$B$151,"missing product") -> Cadbury Biscuits Pack | H278: =_xlfn.XLOOKUP(Sales_Transactions!$F278,Table9[Product_ID],Table9[Category],"Missing Catogory") -> Snacks | I278: STR019 | J278: =_xlfn.XLOOKUP(Sales_Transactions!$I278,Store!$A$2:$A$181,Store!$B$2:$B$181,"Missing Store") -> FreshMart Hyderabad Heights | K278: =_xlfn.XLOOKUP(Sales_Transactions!$I278,Store!$A$2:$A$181,Store!$D$2:$D$181,"East") -> South | L278: EMP0064 | M278: Sanjay Venkataraman | N278: =_xlfn.XLOOKUP(Sales_Transactions!$L278,Table12[Employee_ID],Table12[Department],"Missing Department") -> Cashier | O278: 3 | P278: 125.15 | Q278: 20 | R278: 75.09 | S278: 300.36 | T278: 287.1 | U278: 13.26 | V278: Cash | W278: Not Returned | X278: In-Store | Y278: 10:45 | Z278: Weekday
... A589: INV101010 | B589: 45986 | C589: CUST0462 | D589: =_xlfn.XLOOKUP(Sales_Transactions!$C589,Customer!$A$2:$A$701,Customer!$B$2:$B$701,"Missing") -> Anitha Sharma | E589: =_xlfn.XLOOKUP(Table14[[#This Row],[Customer_ID]],Table10[Customer_ID],Table10[Membership],"Missing Membership") -> Silver | F589: PRD090 | G589: =_xlfn.XLOOKUP(Sales_Transactions!$F589,Products!$A$2:$A$151,Products!$B$2:$B$151,"missing product") -> Organic Fresh Fresh Fruits Pack v2 | H589: =_xlfn.XLOOKUP(Sales_Transactions!$F589,Table9[Product_ID],Table9[Category],"Missing Catogory") -> Fruits | I589: STR088 | J589: =_xlfn.XLOOKUP(Sales_Transactions!$I589,Store!$A$2:$A$181,Store!$B$2:$B$181,"Missing Store") -> FreshMart Salem Extension | K589: =_xlfn.XLOOKUP(Sales_Transactions!$I589,Store!$A$2:$A$181,Store!$D$2:$D$181,"East") -> South | L589: EMP0229 | M589: Udhay Sekar | N589: =_xlfn.XLOOKUP(Sales_Transactions!$L589,Table12[Employee_ID],Table12[Department],"Missing Department") -> Sales | O589: 1 | P589: 438.7 | Q589: 5 | R589: 21.93 | S589: 416.77 | T589: 370.18 | U589: 46.59 | V589: Credit Card | W589: Not Returned | X589: In-Store | Y589: 14:36 | Z589: Weekday
A590: INV101012 | B590: 45839 | C590: CUST0204 | D590: =_xlfn.XLOOKUP(Sales_Transactions!$C590,Customer!$A$2:$A$701,Customer!$B$2:$B$701,"Missing") -> Mala Achari | E590: =_xlfn.XLOOKUP(Table14[[#This Row],[Customer_ID]],Table10[Customer_ID],Table10[Membership],"Missing Membership") -> Gold | F590: PRD029 | G590: =_xlfn.XLOOKUP(Sales_Transactions!$F590,Products!$A$2:$A$151,Products!$B$2:$B$151,"missing product") -> Pepsi Tea 200g | H590: =_xlfn.XLOOKUP(Sales_Transactions!$F590,Table9[Product_ID],Table9[Category],"Missing Catogory") -> Beverages | I590: STR014 | J590: =_xlfn.XLOOKUP(Sales_Transactions!$I590,Store!$A$2:$A$181,Store!$B$2:$B$181,"Missing Store") -> FreshMart Coimbatore Circle | K590: =_xlfn.XLOOKUP(Sales_Transactions!$I590,Store!$A$2:$A$181,Store!$D$2:$D$181,"East") -> South | L590: EMP0241 | M590: Lalitha Krishnan | N590: =_xlfn.XLOOKUP(Sales_Transactions!$L590,Table12[Employee_ID],Table12[Department],"Missing Department") -> Sales | O590: 7 | P590: 339.39 | Q590: 0 | R590: 0 | S590: Rs.2375.73 | T590: 1828.54 | U590: 547.19 | V590: Credit Card | W590: Not Returned | X590: In-Store | Y590: 19:48 | Z590: Weekday
A591: INV101014 | B591: 46110 | C591: CUST0681 | D591: =_xlfn.XLOOKUP(Sales_Transactions!$C591,Customer!$A$2:$A$701,Customer!$B$2:$B$701,"Missing") -> Raghav Iyer | E591: =_xlfn.XLOOKUP(Table14[[#This Row],[Customer_ID]],Table10[Customer_ID],Table10[Membership],"Missing Membership") -> Bronze | F591: PRD021 | G591: =_xlfn.XLOOKUP(Sales_Transactions!$F591,Products!$A$2:$A$151,Products!$B$2:$B$151,"missing product") -> Milky Mist Butter Pack | H591: =_xlfn.XLOOKUP(Sales_Transactions!$F591,Table9[Product_ID],Table9[Category],"Missing Catogory") -> Dairy | I591: STR072 | J591: =_xlfn.XLOOKUP(Sales_Transactions!$I591,Store!$A$2:$A$181,Store!$B$2:$B$181,"Missing Store") -> FreshMart Salem Point | K591: =_xlfn.XLOOKUP(Sales_Transactions!$I591,Store!$A$2:$A$181,Store!$D$2:$D$181,"East") -> South | L591: EMP0124 | M591: Vijay Pandian | N591: =_xlfn.XLOOKUP(Sales_Transactions!$L591,Table12[Employee_ID],Table12[Department],"Missing Department") -> Sales | O591: 1 | P591: 38.66 | Q591: 0 | R591: 0 | S591: 44.46 | T591: 32.4 | U591: 12.06 | V591: Credit Card | W591: Returned | X591: Online | Y591: 21:42 | Z591: Weekend
A592: INV101019 | B592: 45850 | C592: CUST0440 | D592: =_xlfn.XLOOKUP(Sales_Transactions!$C592,Customer!$A$2:$A$701,Customer!$B$2:$B$701,"Missing") -> Yazhini Reddy | E592: =_xlfn.XLOOKUP(Table14[[#This Row],[Customer_ID]],Table10[Customer_ID],Table10[Membership],"Missing Membership") -> Bronze | F592: PRD142 | G592: =_xlfn.XLOOKUP(Sales_Transactions!$F592,Products!$A$2:$A$151,Products!$B$2:$B$151,"missing product") -> Lizol Dishwash 200g | H592: =_xlfn.XLOOKUP(Sales_Transactions!$F592,Table9[Product_ID],Table9[Category],"Missing Catogory") -> Cleaning | I592: STR090 | J592: =_xlfn.XLOOKUP(Sales_Transactions!$I592,Store!$A$2:$A$181,Store!$B$2:$B$181,"Missing Store") -> FreshMart Mysuru Heights | K592: =_xlfn.XLOOKUP(Sales_Transactions!$I592,Store!$A$2:$A$181,Store!$D$2:$D$181,"East") -> South | L592: EMP0262 | M592: Umesh Krishnan | N592: =_xlfn.XLOOKUP(Sales_Transactions!$L592,Table12[Employee_ID],Table12[Department],"Missing Department") -> Sales | O592: 4 | P592: 522.78 | Q592: 5 | R592: 104.56 | S592: 2284.54 | T592: 1583.48 | U592: 701.06 | V592: Credit Card | W592: Not Returned | X592: In-Store | Y592: 20:25 | Z592: Weekend
A593: INV101026 | B593: 45776 | C593: CUST0077 | D593: =_xlfn.XLOOKUP(Sales_Transactions!$C593,Customer!$A$2:$A$701,Customer!$B$2:$B$701,"Missing") -> Dhanya Krishnan | E593: =_xlfn.XLOOKUP(Table14[[#This Row],[Customer_ID]],Table10[Customer_ID],Table10[Membership],"Missing Membership") -> Bronze | F593: PRD137 | G593: =_xlfn.XLOOKUP(Sales_Transactions!$F593,Products!$A$2:$A$151,Products!$B$2:$B$151,"missing product") -> MDH Powdered Spices 200g | H593: =_xlfn.XLOOKUP(Sales_Transactions!$F593,Table9[Product_ID],Table9[Category],"Missing Catogory") -> Masala | I593: STR134 | J593: =_xlfn.XLOOKUP(Sales_Transactions!$I593,Store!$A$2:$A$181,Store!$B$2:$B$181,"Missing Store") -> FreshMart Pune Extension | K593: =_xlfn.XLOOKUP(Sales_Transactions!$I593,Store!$A$2:$A$181,Store!$D$2:$D$181,"East") -> West | L593: EMP0133 | M593: Deepak Naicker | N593: =_xlfn.XLOOKUP(Sales_Transactions!$L593,Table12[Employee_ID],Table12[Department],"Missing Department") -> Sales | O593: 4 | P593: 442.14 | Q593: 5 | R593: 88.43 | S593: 1680.13 | T593: 1407.48 | U593: 272.65 | V593: Credit Card | W593: Not Returned | X593: Online | Y593: 10:50 | Z593: Weekday
A594: INV101032 | B594: 45995 | C594: CUST0490 | D594: =_xlfn.XLOOKUP(Sales_Transactions!$C594,Customer!$A$2:$A$701,Customer!$B$2:$B$701,"Missing") -> Hema Gounder | E594: =_xlfn.XLOOKUP(Table14[[#This Row],[Customer_ID]],Table10[Customer_ID],Table10[Membership],"Missing Membership") -> Gold | F594: PRD022 | G594: =_xlfn.XLOOKUP(Sales_Transactions!$F594,Products!$A$2:$A$151,Products!$B$2:$B$151,"missing product") -> Aavin Milk Pack | H594: =_xlfn.XLOOKUP(Sales_Transactions!$F594,Table9[Product_ID],Table9[Category],"Missing Catogory") -> Dairy | I594: STR128 | J594: =_xlfn.XLOOKUP(Sales_Transactions!$I594,Store!$A$2:$A$181,Store!$B$2:$B$181,"Missing Store") -> FreshMart Surat Junction | K594: =_xlfn.XLOOKUP(Sales_Transactions!$I594,Store!$A$2:$A$181,Store!$D$2:$D$181,"East") -> West | L594: EMP0257 | M594: Sangeetha Naidu | N594: =_xlfn.XLOOKUP(Sales_Transactions!$L594,Table12[Employee_ID],Table12[Department],"Missing Department") -> Cashier | O594: 6 | P594: 431.29 | Q594: 5 | R594: 129.39 | S594: 2458.35 | T594: 1916.22 | U594: 542.13 | V594: Credit Card | W594: Not Returned | X594: In-Store | Y594: 20:41 | Z594: Weekday
A595: INV101033 | B595: 45757 | C595: CUST0007 | D595: =_xlfn.XLOOKUP(Sales_Transactions!$C595,Customer!$A$2:$A$701,Customer!$B$2:$B$701,"Missing") -> Senthil Pillai | E595: =_xlfn.XLOOKUP(Table14[[#This Row],[Customer_ID]],Table10[Customer_ID],Table10[Membership],"Missing Membership") -> Silver | F595: PRD014 | G595: =_xlfn.XLOOKUP(Sales_Transactions!$F595,Products!$A$2:$A$151,Products!$B$2:$B$151,"missing product") -> Milky Mist Curd 1kg | H595: =_xlfn.XLOOKUP(Sales_Transactions!$F595,Table9[Product_ID],Table9[Category],"Missing Catogory") -> Dairy | I595: STR168 | J595: =_xlfn.XLOOKUP(Sales_Transactions!$I595,Store!$A$2:$A$181,Store!$B$2:$B$181,"Missing Store") -> FreshMart Guwahati Point | K595: =_xlfn.XLOOKUP(Sales_Transactions!$I595,Store!$A$2:$A$181,Store!$D$2:$D$181,"East") -> East | L595: EMP0203 | M595: Hariharan Sekar | N595: =_xlfn.XLOOKUP(Sales_Transactions!$L595,Table12[Employee_ID],Table12[Department],"Missing Department") -> Operations | O595: 2 | P595: 434.65 | Q595: 0 | R595: 0 | S595: 869.3 | T595: 703.26 | U595: 166.04 | V595: Credit Card | W595: Not Returned | X595: In-Store | Y595: 16:42 | Z595: Weekday
A596: INV101035 | B596: 45861 | C596: CUST0191 | D596: =_xlfn.XLOOKUP(Sales_Transactions!$C596,Customer!$A$2:$A$701,Customer!$B$2:$B$701,"Missing") -> Elango Balan | E596: =_xlfn.XLOOKUP(Table14[[#This Row],[Customer_ID]],Table10[Customer_ID],Table10[Membership],"Missing Membership") -> Bronze | F596: PRD051 | G596: =_xlfn.XLOOKUP(Sales_Transactions!$F596,Products!$A$2:$A$151,Products!$B$2:$B$151,"missing product") -> Cadbury Biscuits 250ml | H596: =_xlfn.XLOOKUP(Sales_Transactions!$F596,Table9[Product_ID],Table9[Category],"Missing Catogory") -> Snacks | I596: STR146 | J596: =_xlfn.XLOOKUP(Sales_Transactions!$I596,Store!$A$2:$A$181,Store!$B$2:$B$181,"Missing Store") -> FreshMart Chandigarh Hub | K596: =_xlfn.XLOOKUP(Sales_Transactions!$I596,Store!$A$2:$A$181,Store!$D$2:$D$181,"East") -> North | L596: EMP0260 | M596: Kamala Prabhu | N596: =_xlfn.XLOOKUP(Sales_Transactions!$L596,Table12[Employee_ID],Table12[Department],"Missing Department") -> Billing | O596: 1 | P596: 147.97 | Q596: 10 | R596: 14.8 | S596: 133.17 | T596: 112.8 | U596: 20.37 | V596: Credit Card | W596: Not Returned | X596: In-Store | Y596: 16:02 | Z596: Weekday
A597: INV101042 | B597: 45965 | C597: CUST0443 | D597: =_xlfn.XLOOKUP(Sales_Transactions!$C597,Customer!$A$2:$A$701,Customer!$B$2:$B$701,"Missing") -> Suresh Naicker | E597: =_xlfn.XLOOKUP(Table14[[#This Row],[Customer_ID]],Table10[Customer_ID],Table10[Membership],"Missing Membership") -> Bronze | F597: PRD098 | G597: =_xlfn.XLOOKUP(Sales_Transactions!$F597,Products!$A$2:$A$151,Products!$B$2:$B$151,"missing product") -> Organic Fresh Fresh Vegetables 250ml | H597: =_xlfn.XLOOKUP(Sales_Transactions!$F597,Table9[Product_ID],Table9[Category],"Missing Catogory") -> Vegetables | I597: STR063 | J597: =_xlfn.XLOOKUP(Sales_Transactions!$I597,Store!$A$2:$A$181,Store!$B$2:$B$181,"Missing Store") -> FreshMart Hyderabad Market | K597: =_xlfn.XLOOKUP(Sales_Transactions!$I597,Store!$A$2:$A$181,Store!$D$2:$D$181,"East") -> South | L597: EMP0160 | M597: Sangeetha Pillai | N597: =_xlfn.XLOOKUP(Sales_Transactions!$L597,Table12[Employee_ID],Table12[Department],"Missing Department") -> Sales | O597: 1 | P597: 83.13 | Q597: 20 | R597: 16.63 | S597: 66.5 | T597: 69.09 | U597: -2.59 | V597: Credit Card | W597: Not Returned | X597: Online | Y597: 17:09 | Z597: Weekday
A598: INV101045 | B598: 45928 | C598: CUST0151 | D598: =_xlfn.XLOOKUP(Sales_Transactions!$C598,Customer!$A$2:$A$701,Customer!$B$2:$B$701,"Missing") -> Gopal Selvam | E598: =_xlfn.XLOOKUP(Table14[[#This Row],[Customer_ID]],Table10[Customer_ID],Table10[Membership],"Missing Membership") -> Silver | F598: PRD069 | G598: =_xlfn.XLOOKUP(Sales_Transactions!$F598,Products!$A$2:$A$151,Products!$B$2:$B$151,"missing product") -> Patanjali Shampoo 1kg | H598: =_xlfn.XLOOKUP(Sales_Transactions!$F598,Table9[Product_ID],Table9[Category],"Missing Catogory") -> Personal Care | I598: STR152 | J598: =_xlfn.XLOOKUP(Sales_Transactions!$I598,Store!$A$2:$A$181,Store!$B$2:$B$181,"Missing Store") -> FreshMart Lucknow Arcade | K598: =_xlfn.XLOOKUP(Sales_Transactions!$I598,Store!$A$2:$A$181,Store!$D$2:$D$181,"East") -> North | L598: EMP0291 | M598: Sathish Nathan | N598: =_xlfn.XLOOKUP(Sales_Transactions!$L598,Table12[Employee_ID],Table12[Department],"Missing Department") -> HR | O598: 2 | P598: 468.94 | Q598: 15 | R598: 140.68 | S598: 916.78 | T598: 673.6 | U598: 243.18 | V598: Credit Card | W598: Not Returned | X598: In-Store | Y598: 12:03 | Z598: Weekend
A599: INV101051 | B599: 45805 | C599: CUST0506 | D599: =_xlfn.XLOOKUP(Sales_Transactions!$C599,Customer!$A$2:$A$701,Customer!$B$2:$B$701,"Missing") -> Pandi Subramaniam | E599: =_xlfn.XLOOKUP(Table14[[#This Row],[Customer_ID]],Table10[Customer_ID],Table10[Membership],"Missing Membership") -> Gold | F599: PRD027 | G599: =_xlfn.XLOOKUP(Sales_Transactions!$F599,Products!$A$2:$A$151,Products!$B$2:$B$151,"missing product") -> Coca-Cola Tea 1kg | H599: =_xlfn.XLOOKUP(Sales_Transactions!$F599,Table9[Product_ID],Table9[Category],"Missing Catogory") -> Beverages | I599: STR087 | J599: =_xlfn.XLOOKUP(Sales_Transactions!$I599,Store!$A$2:$A$181,Store!$B$2:$B$181,"Missing Store") -> FreshMart Mysuru Complex | K599: =_xlfn.XLOOKUP(Sales_Transactions!$I599,Store!$A$2:$A$181,Store!$D$2:$D$181,"East") -> South | L599: EMP0222 | M599: Poornima Rao | N599: =_xlfn.XLOOKUP(Sales_Transactions!$L599,Table12[Employee_ID],Table12[Department],"Missing Department") -> Inventory | O599: 8 | P599: 155.34 | Q599: 15 | R599: 186.41 | S599: 1056.31 | T599: 855.92 | U599: 200.39 | V599: Credit Card | W599: Not Returned | X599: Online | Y599: 13:24 | Z599: Weekday
A600: INV101070 | B600: 46005 | C600: CUST0446 | D600: =_xlfn.XLOOKUP(Sales_Transactions!$C600,Customer!$A$2:$A$701,Customer!$B$2:$B$701,"Missing") -> Ramesh Sharma | E600: =_xlfn.XLOOKUP(Table14[[#This Row],[Customer_ID]],Table10[Customer_ID],Table10[Membership],"Missing Membership") -> Silver | F600: PRD052 | G600: =_xlfn.XLOOKUP(Sales_Transactions!$F600,Products!$A$2:$A$151,Products!$B$2:$B$151,"missing product") -> Lays Namkeen 200g | H600: =_xlfn.XLOOKUP(Sales_Transactions!$F600,Table9[Product_ID],Table9[Category],"Missing Catogory") -> Snacks | I600: STR108 | J600: =_xlfn.XLOOKUP(Sales_Transactions!$I600,Store!$A$2:$A$181,Store!$B$2:$B$181,"Missing Store") -> FreshMart Mumbai Square | K600: =_xlfn.XLOOKUP(Sales_Transactions!$I600,Store!$A$2:$A$181,Store!$D$2:$D$181,"East") -> West | L600: EMP0171 | M600: Ashok Nair | N600: =_xlfn.XLOOKUP(Sales_Transactions!$L600,Table12[Employee_ID],Table12[Department],"Missing Department") -> Cashier | O600: 4 | P600: 328.59 | Q600: 0 | R600: 0 | S600: 1511.51 | T600: 1021.96 | U600: 489.55 | V600: Credit Card | W600: Not Returned | X600: Online | Y600: 20:45 | Z600: Weekend
A601: INV101072 | B601: 46066 | C601: CUST0086 | D601: =_xlfn.XLOOKUP(Sales_Transactions!$C601,Customer!$A$2:$A$701,Customer!$B$2:$B$701,"Missing") -> Anjali Prabhu | E601: =_xlfn.XLOOKUP(Table14[[#This Row],[Customer_ID]],Table10[Customer_ID],Table10[Membership],"Missing Membership") -> Silver | F601: PRD026 | G601: =_xlfn.XLOOKUP(Sales_Transactions!$F601,Products!$A$2:$A$151,Products!$B$2:$B$151,"missing product") -> Nescafe Coffee 1kg | H601: =_xlfn.XLOOKUP(Sales_Transactions!$F601,Table9[Product_ID],Table9[Category],"Missing Catogory") -> Beverages | I601: STR097 | J601: =_xlfn.XLOOKUP(Sales_Transactions!$I601,Store!$A$2:$A$181,Store!$B$2:$B$181,"Missing Store") -> FreshMart Ahmedabad Arcade | K601: =_xlfn.XLOOKUP(Sales_Transactions!$I601,Store!$A$2:$A$181,Store!$D$2:$D$181,"East") -> West | L601: EMP0146 | M601: Kishore Chettiar | N601: =_xlfn.XLOOKUP(Sales_Transactions!$L601,Table12[Employee_ID],Table12[Department],"Missing Department") -> Inventory | O601: 5 | P601: 329.69 | Q601: 15 | R601: 247.27 | S601: 1401.18 | T601: 1236.25 | U601: 164.93 | V601: Credit Card | W601: Not Returned | X601: In-Store | Y601: 12:39 | Z601: Weekday
A602: INV101097 | B602: 46054 | C602: CUST0053 | D602: =_xlfn.XLOOKUP(Sales_Transactions!$C602,Customer!$A$2:$A$701,Customer!$B$2:$B$701,"Missing") -> Suresh Chettiar | E602: =_xlfn.XLOOKUP(Table14[[#This Row],[Customer_ID]],Table10[Customer_ID],Table10[Membership],"Missing Membership") -> Bronze | F602: PRD023 | G602: =_xlfn.XLOOKUP(Sales_Transactions!$F602,Products!$A$2:$A$151,Products!$B$2:$B$151,"missing product") -> Amul Butter 1L | H602: =_xlfn.XLOOKUP(Sales_Transactions!$F602,Table9[Product_ID],Table9[Category],"Missing Catogory") -> Dairy | I602: STR142 | J602: =_xlfn.XLOOKUP(Sales_Transactions!$I602,Store!$A$2:$A$181,Store!$B$2:$B$181,"Missing Store") -> FreshMart Chandigarh Plaza | K602: =_xlfn.XLOOKUP(Sales_Transactions!$I602,Store!$A$2:$A$181,Store!$D$2:$D$181,"East") -> North | L602: EMP0022 | M602: Banu Gounder | N602: =_xlfn.XLOOKUP(Sales_Transactions!$L602,Table12[Employee_ID],Table12[Department],"Missing Department") -> Sales | O602: 2 | P602: 342.27 | Q602: 5 | R602: 34.23 | S602: 747.86 | T602: 532.2 | U602: 215.66 | V602: Credit Card | W602: Not Returned | X602: In-Store | Y602: 21:59 | Z602: Weekend
... A716: INV101859 | B716: 46112 | C716: CUST0474 | D716: =_xlfn.XLOOKUP(Sales_Transactions!$C716,Customer!$A$2:$A$701,Customer!$B$2:$B$701,"Missing") -> Geetha Venkataraman | E716: =_xlfn.XLOOKUP(Table14[[#This Row],[Customer_ID]],Table10[Customer_ID],Table10[Membership],"Missing Membership") -> Bronze | F716: PRD017 | G716: =_xlfn.XLOOKUP(Sales_Transactions!$F716,Products!$A$2:$A$151,Products!$B$2:$B$151,"missing product") -> Nestle Curd 1kg | H716: =_xlfn.XLOOKUP(Sales_Transactions!$F716,Table9[Product_ID],Table9[Category],"Missing Catogory") -> Dairy | I716: STR089 | J716: =_xlfn.XLOOKUP(Sales_Transactions!$I716,Store!$A$2:$A$181,Store!$B$2:$B$181,"Missing Store") -> FreshMart Salem Hub | K716: =_xlfn.XLOOKUP(Sales_Transactions!$I716,Store!$A$2:$A$181,Store!$D$2:$D$181,"East") -> South | L716: EMP0105 | M716: Nagarajan Mudaliar | N716: =_xlfn.XLOOKUP(Sales_Transactions!$L716,Table12[Employee_ID],Table12[Department],"Missing Department") -> Cashier | O716: 2 | P716: 464.41 | Q716: 0 | R716: 0 | S716: 928.82 | T716: 795.38 | U716: 133.44 | V716: Credit Card | W716: Not Returned | X716: In-Store | Y716: 14:52 | Z716: Weekday
A717: INV101862 | B717: 45858 | C717: CUST0046 | D717: =_xlfn.XLOOKUP(Sales_Transactions!$C717,Customer!$A$2:$A$701,Customer!$B$2:$B$701,"Missing") -> Kishore Murugan | E717: =_xlfn.XLOOKUP(Table14[[#This Row],[Customer_ID]],Table10[Customer_ID],Table10[Membership],"Missing Membership") -> Gold | F717: PRD054 | G717: =_xlfn.XLOOKUP(Sales_Transactions!$F717,Products!$A$2:$A$151,Products!$B$2:$B$151,"missing product") -> Lays Namkeen 2kg | H717: =_xlfn.XLOOKUP(Sales_Transactions!$F717,Table9[Product_ID],Table9[Category],"Missing Catogory") -> Snacks | I717: STR099 | J717: =_xlfn.XLOOKUP(Sales_Transactions!$I717,Store!$A$2:$A$181,Store!$B$2:$B$181,"Missing Store") -> FreshMart Nagpur Plaza | K717: =_xlfn.XLOOKUP(Sales_Transactions!$I717,Store!$A$2:$A$181,Store!$D$2:$D$181,"East") -> West | L717: EMP0026 | M717: Nandhini Pandian | N717: =_xlfn.XLOOKUP(Sales_Transactions!$L717,Table12[Employee_ID],Table12[Department],"Missing Department") -> Operations | O717: 7 | P717: 548.45 | Q717: 15 | R717: 575.87 | S717: Rs.3752.77 | T717: 2654.33 | U717: 1098.44 | V717: Credit Card | W717: Not Returned | X717: In-Store | Y717: 20:45 | Z717: Weekend
A718: INV101876 | B718: 45836 | C718: CUST0250 | D718: =_xlfn.XLOOKUP(Sales_Transactions!$C718,Customer!$A$2:$A$701,Customer!$B$2:$B$701,"Missing") -> Nirmala Mudaliar | E718: =_xlfn.XLOOKUP(Table14[[#This Row],[Customer_ID]],Table10[Customer_ID],Table10[Membership],"Missing Membership") -> Bronze | F718: PRD052 | G718: =_xlfn.XLOOKUP(Sales_Transactions!$F718,Products!$A$2:$A$151,Products!$B$2:$B$151,"missing product") -> Lays Namkeen 200g | H718: =_xlfn.XLOOKUP(Sales_Transactions!$F718,Table9[Product_ID],Table9[Category],"Missing Catogory") -> Snacks | I718: STR129 | J718: =_xlfn.XLOOKUP(Sales_Transactions!$I718,Store!$A$2:$A$181,Store!$B$2:$B$181,"Missing Store") -> FreshMart Ahmedabad Heights | K718: =_xlfn.XLOOKUP(Sales_Transactions!$I718,Store!$A$2:$A$181,Store!$D$2:$D$181,"East") -> West | L718: EMP0314 | M718: Naveen Naidu | N718: =_xlfn.XLOOKUP(Sales_Transactions!$L718,Table12[Employee_ID],Table12[Department],"Missing Department") -> Cashier | O718: 3 | P718: 328.59 | Q718: 0 | R718: 0 | S718: 1133.64 | T718: 766.47 | U718: 367.17 | V718: Credit Card | W718: Not Returned | X718: Online | Y718: 21:37 | Z718: Weekend
A719: INV101881 | B719: 46054 | C719: CUST0238 | D719: =_xlfn.XLOOKUP(Sales_Transactions!$C719,Customer!$A$2:$A$701,Customer!$B$2:$B$701,"Missing") -> Balaji Varma | E719: =_xlfn.XLOOKUP(Table14[[#This Row],[Customer_ID]],Table10[Customer_ID],Table10[Membership],"Missing Membership") -> Silver | F719: PRD111 | G719: =_xlfn.XLOOKUP(Sales_Transactions!$F719,Products!$A$2:$A$151,Products!$B$2:$B$151,"missing product") -> Aachi Idli Rice 500g | H719: =_xlfn.XLOOKUP(Sales_Transactions!$F719,Table9[Product_ID],Table9[Category],"Missing Catogory") -> Rice | I719: STR079 | J719: =_xlfn.XLOOKUP(Sales_Transactions!$I719,Store!$A$2:$A$181,Store!$B$2:$B$181,"Missing Store") -> FreshMart Erode Hub | K719: =_xlfn.XLOOKUP(Sales_Transactions!$I719,Store!$A$2:$A$181,Store!$D$2:$D$181,"East") -> South | L719: EMP0295 | M719: Lakshmi Nair | N719: =_xlfn.XLOOKUP(Sales_Transactions!$L719,Table12[Employee_ID],Table12[Department],"Missing Department") -> Inventory | O719: 3 | P719: 225.45 | Q719: 5 | R719: 33.82 | S719: 738.91 | T719: 572.7 | U719: 166.21 | V719: Credit Card | W719: Not Returned | X719: Mobile App | Y719: 20:56 | Z719: Weekend
A720: INV101883 | B720: 45769 | C720: CUST0457 | D720: =_xlfn.XLOOKUP(Sales_Transactions!$C720,Customer!$A$2:$A$701,Customer!$B$2:$B$701,"Missing") -> Nithya Raj | E720: =_xlfn.XLOOKUP(Table14[[#This Row],[Customer_ID]],Table10[Customer_ID],Table10[Membership],"Missing Membership") -> Silver | F720: PRD099 | G720: =_xlfn.XLOOKUP(Sales_Transactions!$F720,Products!$A$2:$A$151,Products!$B$2:$B$151,"missing product") -> Local Farm Fresh Vegetables 200g | H720: =_xlfn.XLOOKUP(Sales_Transactions!$F720,Table9[Product_ID],Table9[Category],"Missing Catogory") -> Vegetables | I720: STR004 | J720: =_xlfn.XLOOKUP(Sales_Transactions!$I720,Store!$A$2:$A$181,Store!$B$2:$B$181,"Missing Store") -> FreshMart Erode Plaza | K720: =_xlfn.XLOOKUP(Sales_Transactions!$I720,Store!$A$2:$A$181,Store!$D$2:$D$181,"East") -> South | L720: EMP0212 | M720: Tamil Pandian | N720: =_xlfn.XLOOKUP(Sales_Transactions!$L720,Table12[Employee_ID],Table12[Department],"Missing Department") -> Billing | O720: 4 | P720: 401.06 | Q720: 15 | R720: 240.64 | S720: 1363.6 | T720: 1389.88 | U720: -26.28 | V720: Credit Card | W720: Not Returned | X720: Mobile App | Y720: 11:07 | Z720: Weekday
A721: INV101894 | B721: 45936 | C721: CUST0361 | D721: =_xlfn.XLOOKUP(Sales_Transactions!$C721,Customer!$A$2:$A$701,Customer!$B$2:$B$701,"Missing") -> Ramesh Achari | E721: =_xlfn.XLOOKUP(Table14[[#This Row],[Customer_ID]],Table10[Customer_ID],Table10[Membership],"Missing Membership") -> Gold | F721: PRD026 | G721: =_xlfn.XLOOKUP(Sales_Transactions!$F721,Products!$A$2:$A$151,Products!$B$2:$B$151,"missing product") -> Nescafe Coffee 1kg | H721: =_xlfn.XLOOKUP(Sales_Transactions!$F721,Table9[Product_ID],Table9[Category],"Missing Catogory") -> Beverages | I721: STR024 | J721: =_xlfn.XLOOKUP(Sales_Transactions!$I721,Store!$A$2:$A$181,Store!$B$2:$B$181,"Missing Store") -> FreshMart Bengaluru Plaza | K721: =_xlfn.XLOOKUP(Sales_Transactions!$I721,Store!$A$2:$A$181,Store!$D$2:$D$181,"East") -> South | L721: EMP0199 | M721: Pandi Naidu | N721: =_xlfn.XLOOKUP(Sales_Transactions!$L721,Table12[Employee_ID],Table12[Department],"Missing Department") -> Sales | O721: 6 | P721: 371.97 | Q721: 0 | R721: 0 | S721: 2231.82 | T721: 1483.5 | U721: 748.32 | V721: Credit Card | W721: Not Returned | X721: In-Store | Y721: 21:31 | Z721: Weekday
A722: INV101904 | B722: 45997 | C722: CUST0679 | D722: =_xlfn.XLOOKUP(Sales_Transactions!$C722,Customer!$A$2:$A$701,Customer!$B$2:$B$701,"Missing") -> Thiru Prabhu | E722: =_xlfn.XLOOKUP(Table14[[#This Row],[Customer_ID]],Table10[Customer_ID],Table10[Membership],"Missing Membership") -> Silver | F722: PRD020 | G722: =_xlfn.XLOOKUP(Sales_Transactions!$F722,Products!$A$2:$A$151,Products!$B$2:$B$151,"missing product") -> Aavin Milk 1L | H722: =_xlfn.XLOOKUP(Sales_Transactions!$F722,Table9[Product_ID],Table9[Category],"Missing Catogory") -> Dairy | I722: STR143 | J722: =_xlfn.XLOOKUP(Sales_Transactions!$I722,Store!$A$2:$A$181,Store!$B$2:$B$181,"Missing Store") -> FreshMart Jaipur Colony | K722: =_xlfn.XLOOKUP(Sales_Transactions!$I722,Store!$A$2:$A$181,Store!$D$2:$D$181,"East") -> North | L722: EMP0338 | M722: Revathi Sekar | N722: =_xlfn.XLOOKUP(Sales_Transactions!$L722,Table12[Employee_ID],Table12[Department],"Missing Department") -> Sales | O722: 4 | P722: 99.93 | Q722: 0 | R722: 0 | S722: 459.68 | T722: 344.2 | U722: 115.48 | V722: Credit Card | W722: Not Returned | X722: Online | Y722: 19:27 | Z722: Weekend
A723: INV101911 | B723: 45933 | C723: CUST0477 | D723: =_xlfn.XLOOKUP(Sales_Transactions!$C723,Customer!$A$2:$A$701,Customer!$B$2:$B$701,"Missing") -> Malathi Gupta | E723: =_xlfn.XLOOKUP(Table14[[#This Row],[Customer_ID]],Table10[Customer_ID],Table10[Membership],"Missing Membership") -> Gold | F723: PRD035 | G723: =_xlfn.XLOOKUP(Sales_Transactions!$F723,Products!$A$2:$A$151,Products!$B$2:$B$151,"missing product") -> Coca-Cola Coffee 500g | H723: =_xlfn.XLOOKUP(Sales_Transactions!$F723,Table9[Product_ID],Table9[Category],"Missing Catogory") -> Beverages | I723: STR124 | J723: =_xlfn.XLOOKUP(Sales_Transactions!$I723,Store!$A$2:$A$181,Store!$B$2:$B$181,"Missing Store") -> FreshMart Ahmedabad Hub | K723: =_xlfn.XLOOKUP(Sales_Transactions!$I723,Store!$A$2:$A$181,Store!$D$2:$D$181,"East") -> West | L723: EMP0149 | M723: Venkat Nathan | N723: =_xlfn.XLOOKUP(Sales_Transactions!$L723,Table12[Employee_ID],Table12[Department],"Missing Department") -> Billing | O723: 8 | P723: 569.8 | Q723: 0 | R723: 0 | S723: 4558.4 | T723: 3118.4 | U723: 1440 | V723: Credit Card | W723: Not Returned | X723: Online | Y723: 09:20 | Z723: Weekday
A724: INV101913 | B724: 46019 | C724: CUST0035 | D724: =_xlfn.XLOOKUP(Sales_Transactions!$C724,Customer!$A$2:$A$701,Customer!$B$2:$B$701,"Missing") -> Balamurugan Sharma | E724: =_xlfn.XLOOKUP(Table14[[#This Row],[Customer_ID]],Table10[Customer_ID],Table10[Membership],"Missing Membership") -> Gold | F724: PRD028 | G724: =_xlfn.XLOOKUP(Sales_Transactions!$F724,Products!$A$2:$A$151,Products!$B$2:$B$151,"missing product") -> Tata Tea Soft Drinks 500g | H724: =_xlfn.XLOOKUP(Sales_Transactions!$F724,Table9[Product_ID],Table9[Category],"Missing Catogory") -> Beverages | I724: STR087 | J724: =_xlfn.XLOOKUP(Sales_Transactions!$I724,Store!$A$2:$A$181,Store!$B$2:$B$181,"Missing Store") -> FreshMart Mysuru Complex | K724: =_xlfn.XLOOKUP(Sales_Transactions!$I724,Store!$A$2:$A$181,Store!$D$2:$D$181,"East") -> South | L724: EMP0222 | M724: Poornima Rao | N724: =_xlfn.XLOOKUP(Sales_Transactions!$L724,Table12[Employee_ID],Table12[Department],"Missing Department") -> Inventory | O724: 6 | P724: 422.63 | Q724: 0 | R724: 0 | S724: 2916.15 | T724: 1859.88 | U724: 1056.27 | V724: Credit Card | W724: Not Returned | X724: Mobile App | Y724: 16:12 | Z724: Weekend
A725: INV101919 | B725: 45877 | C725: CUST0461 | D725: =_xlfn.XLOOKUP(Sales_Transactions!$C725,Customer!$A$2:$A$701,Customer!$B$2:$B$701,"Missing") -> Prakash Achari | E725: =_xlfn.XLOOKUP(Table14[[#This Row],[Customer_ID]],Table10[Customer_ID],Table10[Membership],"Missing Membership") -> Gold | F725: PRD044 | G725: =_xlfn.XLOOKUP(Sales_Transactions!$F725,Products!$A$2:$A$151,Products!$B$2:$B$151,"missing product") -> ITC Frozen Vegetables 250ml v2 | H725: =_xlfn.XLOOKUP(Sales_Transactions!$F725,Table9[Product_ID],Table9[Category],"Missing Catogory") -> Frozen Foods | I725: STR144 | J725: =_xlfn.XLOOKUP(Sales_Transactions!$I725,Store!$A$2:$A$181,Store!$B$2:$B$181,"Missing Store") -> FreshMart Kanpur Colony | K725: =_xlfn.XLOOKUP(Sales_Transactions!$I725,Store!$A$2:$A$181,Store!$D$2:$D$181,"East") -> North | L725: EMP0047 | M725: Sundar Gounder | N725: =_xlfn.XLOOKUP(Sales_Transactions!$L725,Table12[Employee_ID],Table12[Department],"Missing Department") -> Store Manager | O725: 6 | P725: 261.61 | Q725: 20 | R725: 313.93 | S725: 1255.73 | T725: 1249.32 | U725: 6.41 | V725: Credit Card | W725: Not Returned | X725: In-Store | Y725: 16:29 | Z725: Weekday
A726: INV101924 | B726: 46087 | C726: CUST0517 | D726: =_xlfn.XLOOKUP(Sales_Transactions!$C726,Customer!$A$2:$A$701,Customer!$B$2:$B$701,"Missing") -> Tamil Varma | E726: =_xlfn.XLOOKUP(Table14[[#This Row],[Customer_ID]],Table10[Customer_ID],Table10[Membership],"Missing Membership") -> Silver | F726: PRD085 | G726: =_xlfn.XLOOKUP(Sales_Transactions!$F726,Products!$A$2:$A$151,Products!$B$2:$B$151,"missing product") -> Local Farm Fresh Fruits 1kg | H726: =_xlfn.XLOOKUP(Sales_Transactions!$F726,Table9[Product_ID],Table9[Category],"Missing Catogory") -> Fruits | I726: STR145 | J726: =_xlfn.XLOOKUP(Sales_Transactions!$I726,Store!$A$2:$A$181,Store!$B$2:$B$181,"Missing Store") -> FreshMart Lucknow Main Road | K726: =_xlfn.XLOOKUP(Sales_Transactions!$I726,Store!$A$2:$A$181,Store!$D$2:$D$181,"East") -> North | L726: EMP0161 | M726: Lokesh Venkataraman | N726: =_xlfn.XLOOKUP(Sales_Transactions!$L726,Table12[Employee_ID],Table12[Department],"Missing Department") -> Inventory | O726: 5 | P726: 389.61 | Q726: 0 | R726: 0 | S726: 1948.05 | T726: 1680.35 | U726: 267.7 | V726: Credit Card | W726: Not Returned | X726: In-Store | Y726: 17:15 | Z726: Weekday
A727: INV101938 | B727: 46003 | C727: CUST0206 | D727: =_xlfn.XLOOKUP(Sales_Transactions!$C727,Customer!$A$2:$A$701,Customer!$B$2:$B$701,"Missing") -> Devi Venkataraman | E727: =_xlfn.XLOOKUP(Table14[[#This Row],[Customer_ID]],Table10[Customer_ID],Table10[Membership],"Missing Membership") -> Gold | F727: PRD111 | G727: =_xlfn.XLOOKUP(Sales_Transactions!$F727,Products!$A$2:$A$151,Products!$B$2:$B$151,"missing product") -> Aachi Idli Rice 500g | H727: =_xlfn.XLOOKUP(Sales_Transactions!$F727,Table9[Product_ID],Table9[Category],"Missing Catogory") -> Rice | I727: STR173 | J727: =_xlfn.XLOOKUP(Sales_Transactions!$I727,Store!$A$2:$A$181,Store!$B$2:$B$181,"Missing Store") -> FreshMart Kolkata Main Road | K727: =_xlfn.XLOOKUP(Sales_Transactions!$I727,Store!$A$2:$A$181,Store!$D$2:$D$181,"East") -> East | L727: EMP0019 | M727: Missing Employee Name | N727: =_xlfn.XLOOKUP(Sales_Transactions!$L727,Table12[Employee_ID],Table12[Department],"Missing Department") -> Sales | O727: 7 | P727: 249.05 | Q727: 20 | R727: 348.67 | S727: 1394.68 | T727: 1336.3 | U727: 58.38 | V727: Credit Card | W727: Not Returned | X727: In-Store | Y727: 17:04 | Z727: Weekday
A728: INV101942 | B728: 45960 | C728: CUST0264 | D728: =_xlfn.XLOOKUP(Sales_Transactions!$C728,Customer!$A$2:$A$701,Customer!$B$2:$B$701,"Missing") -> Kavya Sharma | E728: =_xlfn.XLOOKUP(Table14[[#This Row],[Customer_ID]],Table10[Customer_ID],Table10[Membership],"Missing Membership") -> Gold | F728: PRD021 | G728: =_xlfn.XLOOKUP(Sales_Transactions!$F728,Products!$A$2:$A$151,Products!$B$2:$B$151,"missing product") -> Milky Mist Butter Pack | H728: =_xlfn.XLOOKUP(Sales_Transactions!$F728,Table9[Product_ID],Table9[Category],"Missing Catogory") -> Dairy | I728: STR105 | J728: =_xlfn.XLOOKUP(Sales_Transactions!$I728,Store!$A$2:$A$181,Store!$B$2:$B$181,"Missing Store") -> FreshMart Ahmedabad Junction | K728: =_xlfn.XLOOKUP(Sales_Transactions!$I728,Store!$A$2:$A$181,Store!$D$2:$D$181,"East") -> West | L728: EMP0089 | M728: Kalpana Balan | N728: =_xlfn.XLOOKUP(Sales_Transactions!$L728,Table12[Employee_ID],Table12[Department],"Missing Department") -> Cashier | O728: 3 | P728: 41.19 | Q728: 0 | R728: 0 | S728: 123.57 | T728: 97.2 | U728: 26.37 | V728: Credit Card | W728: Not Returned | X728: In-Store | Y728: 15:42 | Z728: Weekday
A729: INV101949 | B729: 45802 | C729: CUST0159 | D729: =_xlfn.XLOOKUP(Sales_Transactions!$C729,Customer!$A$2:$A$701,Customer!$B$2:$B$701,"Missing") -> Usha Naicker | E729: =_xlfn.XLOOKUP(Table14[[#This Row],[Customer_ID]],Table10[Customer_ID],Table10[Membership],"Missing Membership") -> Silver | F729: PRD026 | G729: =_xlfn.XLOOKUP(Sales_Transactions!$F729,Products!$A$2:$A$151,Products!$B$2:$B$151,"missing product") -> Nescafe Coffee 1kg | H729: =_xlfn.XLOOKUP(Sales_Transactions!$F729,Table9[Product_ID],Table9[Category],"Missing Catogory") -> Beverages | I729: STR135 | J729: =_xlfn.XLOOKUP(Sales_Transactions!$I729,Store!$A$2:$A$181,Store!$B$2:$B$181,"Missing Store") -> FreshMart Pune Towers | K729: =_xlfn.XLOOKUP(Sales_Transactions!$I729,Store!$A$2:$A$181,Store!$D$2:$D$181,"East") -> West | L729: EMP0201 | M729: Bharath Reddy | N729: =_xlfn.XLOOKUP(Sales_Transactions!$L729,Table12[Employee_ID],Table12[Department],"Missing Department") -> Sales | O729: 5 | P729: 329.69 | Q729: 15 | R729: 247.27 | S729: 1611.36 | T729: 1236.25 | U729: 375.11 | V729: Credit Card | W729: Not Returned | X729: In-Store | Y729: 15:02 | Z729: Weekend
... A793: INV102343 | B793: 45863 | C793: CUST0279 | D793: =_xlfn.XLOOKUP(Sales_Transactions!$C793,Customer!$A$2:$A$701,Customer!$B$2:$B$701,"Missing") -> Ramesh Devi | E793: =_xlfn.XLOOKUP(Table14[[#This Row],[Customer_ID]],Table10[Customer_ID],Table10[Membership],"Missing Membership") -> Gold | F793: PRD146 | G793: =_xlfn.XLOOKUP(Sales_Transactions!$F793,Products!$A$2:$A$151,Products!$B$2:$B$151,"missing product") -> Lizol Floor Cleaner 200g | H793: =_xlfn.XLOOKUP(Sales_Transactions!$F793,Table9[Product_ID],Table9[Category],"Missing Catogory") -> Cleaning | I793: STR006 | J793: =_xlfn.XLOOKUP(Sales_Transactions!$I793,Store!$A$2:$A$181,Store!$B$2:$B$181,"Missing Store") -> FreshMart Mysuru Junction | K793: =_xlfn.XLOOKUP(Sales_Transactions!$I793,Store!$A$2:$A$181,Store!$D$2:$D$181,"East") -> South | L793: EMP0265 | M793: Padma Subramaniam | N793: =_xlfn.XLOOKUP(Sales_Transactions!$L793,Table12[Employee_ID],Table12[Department],"Missing Department") -> Operations | O793: 5 | P793: 66.99 | Q793: 5 | R793: 16.75 | S793: 318.2 | T793: 249.95 | U793: 68.25 | V793: Credit Card | W793: Not Returned | X793: In-Store | Y793: 17:20 | Z793: Weekday
A794: INV102344 | B794: 45993 | C794: CUST0209 | D794: =_xlfn.XLOOKUP(Sales_Transactions!$C794,Customer!$A$2:$A$701,Customer!$B$2:$B$701,"Missing") -> Udhay Pandian | E794: =_xlfn.XLOOKUP(Table14[[#This Row],[Customer_ID]],Table10[Customer_ID],Table10[Membership],"Missing Membership") -> Gold | F794: PRD090 | G794: =_xlfn.XLOOKUP(Sales_Transactions!$F794,Products!$A$2:$A$151,Products!$B$2:$B$151,"missing product") -> Organic Fresh Fresh Fruits Pack v2 | H794: =_xlfn.XLOOKUP(Sales_Transactions!$F794,Table9[Product_ID],Table9[Category],"Missing Catogory") -> Fruits | I794: STR021 | J794: =_xlfn.XLOOKUP(Sales_Transactions!$I794,Store!$A$2:$A$181,Store!$B$2:$B$181,"Missing Store") -> FreshMart Madurai Market | K794: =_xlfn.XLOOKUP(Sales_Transactions!$I794,Store!$A$2:$A$181,Store!$D$2:$D$181,"East") -> South | L794: EMP0280 | M794: Hema Mudaliar | N794: =_xlfn.XLOOKUP(Sales_Transactions!$L794,Table12[Employee_ID],Table12[Department],"Missing Department") -> Store Manager | O794: 7 | P794: 492.92 | Q794: 10 | R794: 345.04 | S794: Rs.3105.4 | T794: 2591.26 | U794: 514.14 | V794: Credit Card | W794: Not Returned | X794: In-Store | Y794: 14:34 | Z794: Weekday
A795: INV102347 | B795: 46091 | C795: CUST0562 | D795: =_xlfn.XLOOKUP(Sales_Transactions!$C795,Customer!$A$2:$A$701,Customer!$B$2:$B$701,"Missing") -> Gopal Pandian | E795: =_xlfn.XLOOKUP(Table14[[#This Row],[Customer_ID]],Table10[Customer_ID],Table10[Membership],"Missing Membership") -> Gold | F795: PRD089 | G795: =_xlfn.XLOOKUP(Sales_Transactions!$F795,Products!$A$2:$A$151,Products!$B$2:$B$151,"missing product") -> Organic Fresh Fresh Fruits 500g | H795: =_xlfn.XLOOKUP(Sales_Transactions!$F795,Table9[Product_ID],Table9[Category],"Missing Catogory") -> Fruits | I795: STR074 | J795: =_xlfn.XLOOKUP(Sales_Transactions!$I795,Store!$A$2:$A$181,Store!$B$2:$B$181,"Missing Store") -> FreshMart Mysuru Main Road | K795: =_xlfn.XLOOKUP(Sales_Transactions!$I795,Store!$A$2:$A$181,Store!$D$2:$D$181,"East") -> South | L795: EMP0270 | M795: Priya Venkataraman | N795: =_xlfn.XLOOKUP(Sales_Transactions!$L795,Table12[Employee_ID],Table12[Department],"Missing Department") -> Operations | O795: 8 | P795: 309.81 | Q795: 20 | R795: 495.7 | S795: 1982.78 | T795: 2011.36 | U795: -28.58 | V795: Credit Card | W795: Not Returned | X795: In-Store | Y795: 12:54 | Z795: Weekday
A796: INV102348 | B796: 45810 | C796: CUST0110 | D796: =_xlfn.XLOOKUP(Sales_Transactions!$C796,Customer!$A$2:$A$701,Customer!$B$2:$B$701,"Missing") -> Pandi Chandran | E796: =_xlfn.XLOOKUP(Table14[[#This Row],[Customer_ID]],Table10[Customer_ID],Table10[Membership],"Missing Membership") -> Gold | F796: PRD087 | G796: =_xlfn.XLOOKUP(Sales_Transactions!$F796,Products!$A$2:$A$151,Products!$B$2:$B$151,"missing product") -> Organic Fresh Fresh Fruits Combo | H796: =_xlfn.XLOOKUP(Sales_Transactions!$F796,Table9[Product_ID],Table9[Category],"Missing Catogory") -> Fruits | I796: STR054 | J796: =_xlfn.XLOOKUP(Sales_Transactions!$I796,Store!$A$2:$A$181,Store!$B$2:$B$181,"Missing Store") -> FreshMart Mysuru Plaza | K796: =_xlfn.XLOOKUP(Sales_Transactions!$I796,Store!$A$2:$A$181,Store!$D$2:$D$181,"East") -> South | L796: EMP0018 | M796: Chandran Kumar | N796: =_xlfn.XLOOKUP(Sales_Transactions!$L796,Table12[Employee_ID],Table12[Department],"Missing Department") -> Cashier | O796: 8 | P796: 72.34 | Q796: 5 | R796: 28.94 | S796: 549.78 | T796: 474.96 | U796: 74.82 | V796: Credit Card | W796: Not Returned | X796: In-Store | Y796: 21:09 | Z796: Weekday
A797: INV102352 | B797: 45838 | C797: CUST0088 | D797: =_xlfn.XLOOKUP(Sales_Transactions!$C797,Customer!$A$2:$A$701,Customer!$B$2:$B$701,"Missing") -> Eswari Achari | E797: =_xlfn.XLOOKUP(Table14[[#This Row],[Customer_ID]],Table10[Customer_ID],Table10[Membership],"Missing Membership") -> Silver | F797: PRD057 | G797: =_xlfn.XLOOKUP(Sales_Transactions!$F797,Products!$A$2:$A$151,Products!$B$2:$B$151,"missing product") -> Parle Chocolates 500g | H797: =_xlfn.XLOOKUP(Sales_Transactions!$F797,Table9[Product_ID],Table9[Category],"Missing Catogory") -> Snacks | I797: STR067 | J797: =_xlfn.XLOOKUP(Sales_Transactions!$I797,Store!$A$2:$A$181,Store!$B$2:$B$181,"Missing Store") -> FreshMart Salem Complex | K797: =_xlfn.XLOOKUP(Sales_Transactions!$I797,Store!$A$2:$A$181,Store!$D$2:$D$181,"East") -> South | L797: EMP0247 | M797: Sudha Balan | N797: =_xlfn.XLOOKUP(Sales_Transactions!$L797,Table12[Employee_ID],Table12[Department],"Missing Department") -> Sales | O797: 4 | P797: 317.99 | Q797: 20 | R797: 254.39 | S797: 1017.57 | T797: 940.2 | U797: 77.37 | V797: Credit Card | W797: Not Returned | X797: In-Store | Y797: 09:26 | Z797: Weekday
A798: INV102353 | B798: 45941 | C798: CUST0637 | D798: =_xlfn.XLOOKUP(Sales_Transactions!$C798,Customer!$A$2:$A$701,Customer!$B$2:$B$701,"Missing") -> Deepa Devi | E798: =_xlfn.XLOOKUP(Table14[[#This Row],[Customer_ID]],Table10[Customer_ID],Table10[Membership],"Missing Membership") -> Bronze | F798: PRD027 | G798: =_xlfn.XLOOKUP(Sales_Transactions!$F798,Products!$A$2:$A$151,Products!$B$2:$B$151,"missing product") -> Coca-Cola Tea 1kg | H798: =_xlfn.XLOOKUP(Sales_Transactions!$F798,Table9[Product_ID],Table9[Category],"Missing Catogory") -> Beverages | I798: STR121 | J798: =_xlfn.XLOOKUP(Sales_Transactions!$I798,Store!$A$2:$A$181,Store!$B$2:$B$181,"Missing Store") -> FreshMart Pune Junction | K798: =_xlfn.XLOOKUP(Sales_Transactions!$I798,Store!$A$2:$A$181,Store!$D$2:$D$181,"East") -> West | L798: EMP0319 | M798: Harini Kumar | N798: =_xlfn.XLOOKUP(Sales_Transactions!$L798,Table12[Employee_ID],Table12[Department],"Missing Department") -> Cashier | O798: 4 | P798: 139.21 | Q798: 20 | R798: 111.37 | S798: 512.29 | T798: 427.96 | U798: 84.33 | V798: Credit Card | W798: Not Returned | X798: In-Store | Y798: 10:27 | Z798: Weekend
A799: INV102358 | B799: 45955 | C799: CUST0058 | D799: =_xlfn.XLOOKUP(Sales_Transactions!$C799,Customer!$A$2:$A$701,Customer!$B$2:$B$701,"Missing") -> Tara Devi | E799: =_xlfn.XLOOKUP(Table14[[#This Row],[Customer_ID]],Table10[Customer_ID],Table10[Membership],"Missing Membership") -> Gold | F799: PRD084 | G799: =_xlfn.XLOOKUP(Sales_Transactions!$F799,Products!$A$2:$A$151,Products!$B$2:$B$151,"missing product") -> Local Farm Fresh Fruits Combo | H799: =_xlfn.XLOOKUP(Sales_Transactions!$F799,Table9[Product_ID],Table9[Category],"Missing Catogory") -> Fruits | I799: STR059 | J799: =_xlfn.XLOOKUP(Sales_Transactions!$I799,Store!$A$2:$A$181,Store!$B$2:$B$181,"Missing Store") -> FreshMart Coimbatore Plaza | K799: =_xlfn.XLOOKUP(Sales_Transactions!$I799,Store!$A$2:$A$181,Store!$D$2:$D$181,"East") -> South | L799: EMP0283 | M799: Suresh Pandian | N799: =_xlfn.XLOOKUP(Sales_Transactions!$L799,Table12[Employee_ID],Table12[Department],"Missing Department") -> Sales | O799: 7 | P799: 227.52 | Q799: 0 | R799: 0 | S799: 1831.54 | T799: 1275.19 | U799: 556.35 | V799: Credit Card | W799: Not Returned | X799: In-Store | Y799: 17:04 | Z799: Weekend
A800: INV102368 | B800: 46002 | C800: CUST0448 | D800: =_xlfn.XLOOKUP(Sales_Transactions!$C800,Customer!$A$2:$A$701,Customer!$B$2:$B$701,"Missing") -> Sanjay Achari | E800: =_xlfn.XLOOKUP(Table14[[#This Row],[Customer_ID]],Table10[Customer_ID],Table10[Membership],"Missing Membership") -> Silver | F800: PRD140 | G800: =_xlfn.XLOOKUP(Sales_Transactions!$F800,Products!$A$2:$A$151,Products!$B$2:$B$151,"missing product") -> Vim Toilet Cleaner 2kg | H800: =_xlfn.XLOOKUP(Sales_Transactions!$F800,Table9[Product_ID],Table9[Category],"Missing Catogory") -> Cleaning | I800: STR028 | J800: =_xlfn.XLOOKUP(Sales_Transactions!$I800,Store!$A$2:$A$181,Store!$B$2:$B$181,"Missing Store") -> FreshMart Ahmedabad Hub | K800: =_xlfn.XLOOKUP(Sales_Transactions!$I800,Store!$A$2:$A$181,Store!$D$2:$D$181,"East") -> South | L800: EMP0235 | M800: Mani Chandran | N800: =_xlfn.XLOOKUP(Sales_Transactions!$L800,Table12[Employee_ID],Table12[Department],"Missing Department") -> Cashier | O800: 4 | P800: 352.51 | Q800: 20 | R800: 282.01 | S800: 1128.03 | T800: 1040.24 | U800: 87.79 | V800: Credit Card | W800: Not Returned | X800: Online | Y800: 18:24 | Z800: Weekday
A801: INV102384 | B801: 45983 | C801: CUST0076 | D801: =_xlfn.XLOOKUP(Sales_Transactions!$C801,Customer!$A$2:$A$701,Customer!$B$2:$B$701,"Missing") -> Senthil Chandran | E801: =_xlfn.XLOOKUP(Table14[[#This Row],[Customer_ID]],Table10[Customer_ID],Table10[Membership],"Missing Membership") -> Gold | F801: PRD103 | G801: =_xlfn.XLOOKUP(Sales_Transactions!$F801,Products!$A$2:$A$151,Products!$B$2:$B$151,"missing product") -> Organic Fresh Fresh Vegetables Pack | H801: =_xlfn.XLOOKUP(Sales_Transactions!$F801,Table9[Product_ID],Table9[Category],"Missing Catogory") -> Vegetables | I801: STR085 | J801: =_xlfn.XLOOKUP(Sales_Transactions!$I801,Store!$A$2:$A$181,Store!$B$2:$B$181,"Missing Store") -> FreshMart Mysuru Arcade | K801: =_xlfn.XLOOKUP(Sales_Transactions!$I801,Store!$A$2:$A$181,Store!$D$2:$D$181,"East") -> South | L801: EMP0121 | M801: Nithya Selvam | N801: =_xlfn.XLOOKUP(Sales_Transactions!$L801,Table12[Employee_ID],Table12[Department],"Missing Department") -> Cashier | O801: 7 | P801: 397.16 | Q801: 0 | R801: 0 | S801: 3197.14 | T801: 2123.87 | U801: 1073.27 | V801: Credit Card | W801: Not Returned | X801: In-Store | Y801: 20:50 | Z801: Weekend
A802: INV102388 | B802: 46103 | C802: CUST0504 | D802: =_xlfn.XLOOKUP(Sales_Transactions!$C802,Customer!$A$2:$A$701,Customer!$B$2:$B$701,"Missing") -> Kalpana Kumar | E802: =_xlfn.XLOOKUP(Table14[[#This Row],[Customer_ID]],Table10[Customer_ID],Table10[Membership],"Missing Membership") -> Gold | F802: PRD085 | G802: =_xlfn.XLOOKUP(Sales_Transactions!$F802,Products!$A$2:$A$151,Products!$B$2:$B$151,"missing product") -> Local Farm Fresh Fruits 1kg | H802: =_xlfn.XLOOKUP(Sales_Transactions!$F802,Table9[Product_ID],Table9[Category],"Missing Catogory") -> Fruits | I802: STR056 | J802: =_xlfn.XLOOKUP(Sales_Transactions!$I802,Store!$A$2:$A$181,Store!$B$2:$B$181,"Missing Store") -> FreshMart Bengaluru Junction | K802: =_xlfn.XLOOKUP(Sales_Transactions!$I802,Store!$A$2:$A$181,Store!$D$2:$D$181,"East") -> South | L802: EMP0163 | M802: Revathi Raj | N802: =_xlfn.XLOOKUP(Sales_Transactions!$L802,Table12[Employee_ID],Table12[Department],"Missing Department") -> Cashier | O802: 5 | P802: 433.39 | Q802: 0 | R802: 0 | S802: 2491.99 | T802: 1680.35 | U802: 811.64 | V802: Credit Card | W802: Not Returned | X802: In-Store | Y802: 13:16 | Z802: Weekend
A803: INV102396 | B803: 45770 | C803: CUST0277 | D803: =_xlfn.XLOOKUP(Sales_Transactions!$C803,Customer!$A$2:$A$701,Customer!$B$2:$B$701,"Missing") -> Senthil Kumar | E803: =_xlfn.XLOOKUP(Table14[[#This Row],[Customer_ID]],Table10[Customer_ID],Table10[Membership],"Missing Membership") -> Gold | F803: PRD079 | G803: =_xlfn.XLOOKUP(Sales_Transactions!$F803,Products!$A$2:$A$151,Products!$B$2:$B$151,"missing product") -> Eveready Detergent Pack | H803: =_xlfn.XLOOKUP(Sales_Transactions!$F803,Table9[Product_ID],Table9[Category],"Missing Catogory") -> Household | I803: STR149 | J803: =_xlfn.XLOOKUP(Sales_Transactions!$I803,Store!$A$2:$A$181,Store!$B$2:$B$181,"Missing Store") -> FreshMart Jaipur Point | K803: =_xlfn.XLOOKUP(Sales_Transactions!$I803,Store!$A$2:$A$181,Store!$D$2:$D$181,"East") -> North | L803: EMP0332 | M803: Udhay Gounder | N803: =_xlfn.XLOOKUP(Sales_Transactions!$L803,Table12[Employee_ID],Table12[Department],"Missing Department") -> Cashier | O803: 8 | P803: 276.87 | Q803: 5 | R803: 110.75 | S803: 2104.21 | T803: 1552.48 | U803: 551.73 | V803: Credit Card | W803: Not Returned | X803: In-Store | Y803: 16:02 | Z803: Weekday
A804: INV102401 | B804: 45969 | C804: CUST0380 | D804: =_xlfn.XLOOKUP(Sales_Transactions!$C804,Customer!$A$2:$A$701,Customer!$B$2:$B$701,"Missing") -> Dinesh Venkataraman | E804: =_xlfn.XLOOKUP(Table14[[#This Row],[Customer_ID]],Table10[Customer_ID],Table10[Membership],"Missing Membership") -> Silver | F804: PRD017 | G804: =_xlfn.XLOOKUP(Sales_Transactions!$F804,Products!$A$2:$A$151,Products!$B$2:$B$151,"missing product") -> Nestle Curd 1kg | H804: =_xlfn.XLOOKUP(Sales_Transactions!$F804,Table9[Product_ID],Table9[Category],"Missing Catogory") -> Dairy | I804: STR051 | J804: =_xlfn.XLOOKUP(Sales_Transactions!$I804,Store!$A$2:$A$181,Store!$B$2:$B$181,"Missing Store") -> FreshMart Madurai Arcade | K804: =_xlfn.XLOOKUP(Sales_Transactions!$I804,Store!$A$2:$A$181,Store!$D$2:$D$181,"East") -> South | L804: EMP0147 | M804: Hemalatha Naidu | N804: =_xlfn.XLOOKUP(Sales_Transactions!$L804,Table12[Employee_ID],Table12[Department],"Missing Department") -> Billing | O804: 2 | P804: 464.41 | Q804: 0 | R804: 0 | S804: 1068.14 | T804: 795.38 | U804: 272.76 | V804: Credit Card | W804: Not Returned | X804: In-Store | Y804: 20:55 | Z804: Weekend
A805: INV102415 | B805: 45795 | C805: CUST0209 | D805: =_xlfn.XLOOKUP(Sales_Transactions!$C805,Customer!$A$2:$A$701,Customer!$B$2:$B$701,"Missing") -> Udhay Pandian | E805: =_xlfn.XLOOKUP(Table14[[#This Row],[Customer_ID]],Table10[Customer_ID],Table10[Membership],"Missing Membership") -> Gold | F805: PRD066 | G805: =_xlfn.XLOOKUP(Sales_Transactions!$F805,Products!$A$2:$A$151,Products!$B$2:$B$151,"missing product") -> Dove Shampoo 2kg | H805: =_xlfn.XLOOKUP(Sales_Transactions!$F805,Table9[Product_ID],Table9[Category],"Missing Catogory") -> Personal Care | I805: STR017 | J805: =_xlfn.XLOOKUP(Sales_Transactions!$I805,Store!$A$2:$A$181,Store!$B$2:$B$181,"Missing Store") -> FreshMart Madurai Plaza | K805: =_xlfn.XLOOKUP(Sales_Transactions!$I805,Store!$A$2:$A$181,Store!$D$2:$D$181,"East") -> South | L805: EMP0092 | M805: Tara Gupta | N805: =_xlfn.XLOOKUP(Sales_Transactions!$L805,Table12[Employee_ID],Table12[Department],"Missing Department") -> Sales | O805: 3 | P805: 511.56 | Q805: 0 | R805: 0 | S805: 1764.88 | T805: 1096.71 | U805: 668.17 | V805: Credit Card | W805: Not Returned | X805: Online | Y805: 14:02 | Z805: Weekend
A806: INV102416 | B806: 45831 | C806: CUST0611 | D806: =_xlfn.XLOOKUP(Sales_Transactions!$C806,Customer!$A$2:$A$701,Customer!$B$2:$B$701,"Missing") -> Vasanth Iyer | E806: =_xlfn.XLOOKUP(Table14[[#This Row],[Customer_ID]],Table10[Customer_ID],Table10[Membership],"Missing Membership") -> Gold | F806: PRD090 | G806: =_xlfn.XLOOKUP(Sales_Transactions!$F806,Products!$A$2:$A$151,Products!$B$2:$B$151,"missing product") -> Organic Fresh Fresh Fruits Pack v2 | H806: =_xlfn.XLOOKUP(Sales_Transactions!$F806,Table9[Product_ID],Table9[Category],"Missing Catogory") -> Fruits | I806: STR007 | J806: =_xlfn.XLOOKUP(Sales_Transactions!$I806,Store!$A$2:$A$181,Store!$B$2:$B$181,"Missing Store") -> FreshMart Mysuru Towers | K806: =_xlfn.XLOOKUP(Sales_Transactions!$I806,Store!$A$2:$A$181,Store!$D$2:$D$181,"East") -> South | L806: EMP0284 | M806: Naveen Venkataraman | N806: =_xlfn.XLOOKUP(Sales_Transactions!$L806,Table12[Employee_ID],Table12[Department],"Missing Department") -> Sales | O806: 3 | P806: 461.01 | Q806: 15 | R806: 207.45 | S806: 1175.58 | T806: 1110.54 | U806: 65.04 | V806: Credit Card | W806: Not Returned | X806: In-Store | Y806: 20:52 | Z806: Weekday
... A1044: INV101382 | B1044: 46005 | C1044: CUST0474 | D1044: =_xlfn.XLOOKUP(Sales_Transactions!$C1044,Customer!$A$2:$A$701,Customer!$B$2:$B$701,"Missing") -> Geetha Venkataraman | E1044: =_xlfn.XLOOKUP(Table14[[#This Row],[Customer_ID]],Table10[Customer_ID],Table10[Membership],"Missing Membership") -> Bronze | F1044: PRD130 | G1044: =_xlfn.XLOOKUP(Sales_Transactions!$F1044,Products!$A$2:$A$151,Products!$B$2:$B$151,"missing product") -> Aachi Whole Spices 200g | H1044: =_xlfn.XLOOKUP(Sales_Transactions!$F1044,Table9[Product_ID],Table9[Category],"Missing Catogory") -> Masala | I1044: STR127 | J1044: =_xlfn.XLOOKUP(Sales_Transactions!$I1044,Store!$A$2:$A$181,Store!$B$2:$B$181,"Missing Store") -> FreshMart Surat Enclave | K1044: =_xlfn.XLOOKUP(Sales_Transactions!$I1044,Store!$A$2:$A$181,Store!$D$2:$D$181,"East") -> West | L1044: EMP0009 | M1044: Usha Chettiar | N1044: =_xlfn.XLOOKUP(Sales_Transactions!$L1044,Table12[Employee_ID],Table12[Department],"Missing Department") -> Cashier | O1044: 2 | P1044: 519.78 | Q1044: 5 | R1044: 51.98 | S1044: 1135.72 | T1044: 795.84 | U1044: 339.88 | V1044: Debit Card | W1044: Not Returned | X1044: In-Store | Y1044: 20:47 | Z1044: Weekend
A1045: INV101393 | B1045: 46011 | C1045: CUST0238 | D1045: =_xlfn.XLOOKUP(Sales_Transactions!$C1045,Customer!$A$2:$A$701,Customer!$B$2:$B$701,"Missing") -> Balaji Varma | E1045: =_xlfn.XLOOKUP(Table14[[#This Row],[Customer_ID]],Table10[Customer_ID],Table10[Membership],"Missing Membership") -> Silver | F1045: PRD110 | G1045: =_xlfn.XLOOKUP(Sales_Transactions!$F1045,Products!$A$2:$A$151,Products!$B$2:$B$151,"missing product") -> India Gate Ponni Rice 1kg | H1045: =_xlfn.XLOOKUP(Sales_Transactions!$F1045,Table9[Product_ID],Table9[Category],"Missing Catogory") -> Rice | I1045: STR080 | J1045: =_xlfn.XLOOKUP(Sales_Transactions!$I1045,Store!$A$2:$A$181,Store!$B$2:$B$181,"Missing Store") -> FreshMart Madurai Colony | K1045: =_xlfn.XLOOKUP(Sales_Transactions!$I1045,Store!$A$2:$A$181,Store!$D$2:$D$181,"East") -> South | L1045: EMP0285 | M1045: Lalitha Murugan | N1045: =_xlfn.XLOOKUP(Sales_Transactions!$L1045,Table12[Employee_ID],Table12[Department],"Missing Department") -> Store Manager | O1045: 3 | P1045: 291.93 | Q1045: 15 | R1045: 131.37 | S1045: Rs.856.08 | T1045: 761.1 | U1045: 94.98 | V1045: Debit Card | W1045: Not Returned | X1045: Mobile App | Y1045: 17:45 | Z1045: Weekend
A1046: INV101395 | B1046: 45958 | C1046: CUST0097 | D1046: =_xlfn.XLOOKUP(Sales_Transactions!$C1046,Customer!$A$2:$A$701,Customer!$B$2:$B$701,"Missing") -> Deepak Prabhu | E1046: =_xlfn.XLOOKUP(Table14[[#This Row],[Customer_ID]],Table10[Customer_ID],Table10[Membership],"Missing Membership") -> Bronze | F1046: PRD032 | G1046: =_xlfn.XLOOKUP(Sales_Transactions!$F1046,Products!$A$2:$A$151,Products!$B$2:$B$151,"missing product") -> Coca-Cola Coffee Combo | H1046: =_xlfn.XLOOKUP(Sales_Transactions!$F1046,Table9[Product_ID],Table9[Category],"Missing Catogory") -> Beverages | I1046: STR095 | J1046: =_xlfn.XLOOKUP(Sales_Transactions!$I1046,Store!$A$2:$A$181,Store!$B$2:$B$181,"Missing Store") -> FreshMart Ahmedabad Gardens | K1046: =_xlfn.XLOOKUP(Sales_Transactions!$I1046,Store!$A$2:$A$181,Store!$D$2:$D$181,"East") -> West | L1046: EMP0201 | M1046: Bharath Reddy | N1046: =_xlfn.XLOOKUP(Sales_Transactions!$L1046,Table12[Employee_ID],Table12[Department],"Missing Department") -> Sales | O1046: 3 | P1046: 141.11 | Q1046: 0 | R1046: 0 | S1046: 423.33 | T1046: 347.73 | U1046: 75.6 | V1046: Debit Card | W1046: Not Returned | X1046: In-Store | Y1046: 13:05 | Z1046: Weekday
A1047: INV101397 | B1047: 45985 | C1047: CUST0541 | D1047: =_xlfn.XLOOKUP(Sales_Transactions!$C1047,Customer!$A$2:$A$701,Customer!$B$2:$B$701,"Missing") -> Divya Reddy | E1047: =_xlfn.XLOOKUP(Table14[[#This Row],[Customer_ID]],Table10[Customer_ID],Table10[Membership],"Missing Membership") -> Gold | F1047: PRD094 | G1047: =_xlfn.XLOOKUP(Sales_Transactions!$F1047,Products!$A$2:$A$151,Products!$B$2:$B$151,"missing product") -> Organic Fresh Fresh Vegetables 2kg | H1047: =_xlfn.XLOOKUP(Sales_Transactions!$F1047,Table9[Product_ID],Table9[Category],"Missing Catogory") -> Vegetables | I1047: STR097 | J1047: =_xlfn.XLOOKUP(Sales_Transactions!$I1047,Store!$A$2:$A$181,Store!$B$2:$B$181,"Missing Store") -> FreshMart Ahmedabad Arcade | K1047: =_xlfn.XLOOKUP(Sales_Transactions!$I1047,Store!$A$2:$A$181,Store!$D$2:$D$181,"East") -> West | L1047: EMP0340 | M1047: Nithya Subramaniam | N1047: =_xlfn.XLOOKUP(Sales_Transactions!$L1047,Table12[Employee_ID],Table12[Department],"Missing Department") -> Cashier | O1047: 4 | P1047: 332.05 | Q1047: 15 | R1047: 199.23 | S1047: 1128.97 | T1047: 1002.76 | U1047: 126.21 | V1047: Debit Card | W1047: Not Returned | X1047: In-Store | Y1047: 21:21 | Z1047: Weekday
A1048: INV101403 | B1048: 46009 | C1048: CUST0063 | D1048: =_xlfn.XLOOKUP(Sales_Transactions!$C1048,Customer!$A$2:$A$701,Customer!$B$2:$B$701,"Missing") -> Priya Varma | E1048: =_xlfn.XLOOKUP(Table14[[#This Row],[Customer_ID]],Table10[Customer_ID],Table10[Membership],"Missing Membership") -> Gold | F1048: PRD068 | G1048: =_xlfn.XLOOKUP(Sales_Transactions!$F1048,Products!$A$2:$A$151,Products!$B$2:$B$151,"missing product") -> Patanjali Shampoo 2kg | H1048: =_xlfn.XLOOKUP(Sales_Transactions!$F1048,Table9[Product_ID],Table9[Category],"Missing Catogory") -> Personal Care | I1048: STR081 | J1048: =_xlfn.XLOOKUP(Sales_Transactions!$I1048,Store!$A$2:$A$181,Store!$B$2:$B$181,"Missing Store") -> FreshMart Erode Crossing | K1048: =_xlfn.XLOOKUP(Sales_Transactions!$I1048,Store!$A$2:$A$181,Store!$D$2:$D$181,"East") -> South | L1048: EMP0186 | M1048: Hemalatha Velan | N1048: =_xlfn.XLOOKUP(Sales_Transactions!$L1048,Table12[Employee_ID],Table12[Department],"Missing Department") -> Billing | O1048: 8 | P1048: 253.59 | Q1048: 15 | R1048: 304.31 | S1048: 1724.41 | T1048: 1287.84 | U1048: 436.57 | V1048: Debit Card | W1048: Not Returned | X1048: In-Store | Y1048: 14:38 | Z1048: Weekday
A1049: INV101407 | B1049: 46096 | C1049: CUST0225 | D1049: =_xlfn.XLOOKUP(Sales_Transactions!$C1049,Customer!$A$2:$A$701,Customer!$B$2:$B$701,"Missing") -> Raghav Naicker | E1049: =_xlfn.XLOOKUP(Table14[[#This Row],[Customer_ID]],Table10[Customer_ID],Table10[Membership],"Missing Membership") -> Silver | F1049: PRD027 | G1049: =_xlfn.XLOOKUP(Sales_Transactions!$F1049,Products!$A$2:$A$151,Products!$B$2:$B$151,"missing product") -> Coca-Cola Tea 1kg | H1049: =_xlfn.XLOOKUP(Sales_Transactions!$F1049,Table9[Product_ID],Table9[Category],"Missing Catogory") -> Beverages | I1049: STR096 | J1049: =_xlfn.XLOOKUP(Sales_Transactions!$I1049,Store!$A$2:$A$181,Store!$B$2:$B$181,"Missing Store") -> FreshMart Mumbai Bypass | K1049: =_xlfn.XLOOKUP(Sales_Transactions!$I1049,Store!$A$2:$A$181,Store!$D$2:$D$181,"East") -> West | L1049: EMP0301 | M1049: Kalpana Prabhu | N1049: =_xlfn.XLOOKUP(Sales_Transactions!$L1049,Table12[Employee_ID],Table12[Department],"Missing Department") -> Inventory | O1049: 3 | P1049: 139.21 | Q1049: 20 | R1049: 83.53 | S1049: 384.21 | T1049: 320.97 | U1049: 63.24 | V1049: Debit Card | W1049: Not Returned | X1049: In-Store | Y1049: 14:38 | Z1049: Weekend
A1050: INV101419 | B1050: 45813 | C1050: CUST0699 | D1050: =_xlfn.XLOOKUP(Sales_Transactions!$C1050,Customer!$A$2:$A$701,Customer!$B$2:$B$701,"Missing") -> Karthik Iyer | E1050: =_xlfn.XLOOKUP(Table14[[#This Row],[Customer_ID]],Table10[Customer_ID],Table10[Membership],"Missing Membership") -> Gold | F1050: PRD089 | G1050: =_xlfn.XLOOKUP(Sales_Transactions!$F1050,Products!$A$2:$A$151,Products!$B$2:$B$151,"missing product") -> Organic Fresh Fresh Fruits 500g | H1050: =_xlfn.XLOOKUP(Sales_Transactions!$F1050,Table9[Product_ID],Table9[Category],"Missing Catogory") -> Fruits | I1050: STR022 | J1050: =_xlfn.XLOOKUP(Sales_Transactions!$I1050,Store!$A$2:$A$181,Store!$B$2:$B$181,"Missing Store") -> FreshMart Tiruppur Complex | K1050: =_xlfn.XLOOKUP(Sales_Transactions!$I1050,Store!$A$2:$A$181,Store!$D$2:$D$181,"East") -> South | L1050: EMP0283 | M1050: Suresh Pandian | N1050: =_xlfn.XLOOKUP(Sales_Transactions!$L1050,Table12[Employee_ID],Table12[Department],"Missing Department") -> Sales | O1050: 7 | P1050: 345 | Q1050: 10 | R1050: 241.5 | S1050: 2173.5 | T1050: 1759.94 | U1050: 413.56 | V1050: Debit Card | W1050: Not Returned | X1050: In-Store | Y1050: 13:43 | Z1050: Weekday
A1051: INV101434 | B1051: 45940 | C1051: CUST0662 | D1051: =_xlfn.XLOOKUP(Sales_Transactions!$C1051,Customer!$A$2:$A$701,Customer!$B$2:$B$701,"Missing") -> Balamurugan Nair | E1051: =_xlfn.XLOOKUP(Table14[[#This Row],[Customer_ID]],Table10[Customer_ID],Table10[Membership],"Missing Membership") -> Bronze | F1051: PRD012 | G1051: =_xlfn.XLOOKUP(Sales_Transactions!$F1051,Products!$A$2:$A$151,Products!$B$2:$B$151,"missing product") -> Harvest Gold Rusk 1kg | H1051: =_xlfn.XLOOKUP(Sales_Transactions!$F1051,Table9[Product_ID],Table9[Category],"Missing Catogory") -> Bakery | I1051: STR082 | J1051: =_xlfn.XLOOKUP(Sales_Transactions!$I1051,Store!$A$2:$A$181,Store!$B$2:$B$181,"Missing Store") -> FreshMart Salem Bypass | K1051: =_xlfn.XLOOKUP(Sales_Transactions!$I1051,Store!$A$2:$A$181,Store!$D$2:$D$181,"East") -> South | L1051: EMP0115 | M1051: Vasanth Menon | N1051: =_xlfn.XLOOKUP(Sales_Transactions!$L1051,Table12[Employee_ID],Table12[Department],"Missing Department") -> Store Manager | O1051: 2 | P1051: 541.35 | Q1051: 10 | R1051: 108.27 | S1051: 974.43 | T1051: 672.8 | U1051: 301.63 | V1051: Debit Card | W1051: Not Returned | X1051: Mobile App | Y1051: 15:30 | Z1051: Weekday
A1052: INV101448 | B1052: 46004 | C1052: CUST0587 | D1052: =_xlfn.XLOOKUP(Sales_Transactions!$C1052,Customer!$A$2:$A$701,Customer!$B$2:$B$701,"Missing") -> Uma Iyer | E1052: =_xlfn.XLOOKUP(Table14[[#This Row],[Customer_ID]],Table10[Customer_ID],Table10[Membership],"Missing Membership") -> Bronze | F1052: PRD111 | G1052: =_xlfn.XLOOKUP(Sales_Transactions!$F1052,Products!$A$2:$A$151,Products!$B$2:$B$151,"missing product") -> Aachi Idli Rice 500g | H1052: =_xlfn.XLOOKUP(Sales_Transactions!$F1052,Table9[Product_ID],Table9[Category],"Missing Catogory") -> Rice | I1052: STR007 | J1052: =_xlfn.XLOOKUP(Sales_Transactions!$I1052,Store!$A$2:$A$181,Store!$B$2:$B$181,"Missing Store") -> FreshMart Mysuru Towers | K1052: =_xlfn.XLOOKUP(Sales_Transactions!$I1052,Store!$A$2:$A$181,Store!$D$2:$D$181,"East") -> South | L1052: EMP0124 | M1052: Vijay Pandian | N1052: =_xlfn.XLOOKUP(Sales_Transactions!$L1052,Table12[Employee_ID],Table12[Department],"Missing Department") -> Sales | O1052: 4 | P1052: 225.45 | Q1052: 0 | R1052: 0 | S1052: 1037.07 | T1052: 763.6 | U1052: 273.47 | V1052: Debit Card | W1052: Not Returned | X1052: In-Store | Y1052: 09:22 | Z1052: Weekend
A1053: INV101449 | B1053: 45797 | C1053: CUST0570 | D1053: =_xlfn.XLOOKUP(Sales_Transactions!$C1053,Customer!$A$2:$A$701,Customer!$B$2:$B$701,"Missing") -> Banu Iyer | E1053: =_xlfn.XLOOKUP(Table14[[#This Row],[Customer_ID]],Table10[Customer_ID],Table10[Membership],"Missing Membership") -> Silver | F1053: PRD035 | G1053: =_xlfn.XLOOKUP(Sales_Transactions!$F1053,Products!$A$2:$A$151,Products!$B$2:$B$151,"missing product") -> Coca-Cola Coffee 500g | H1053: =_xlfn.XLOOKUP(Sales_Transactions!$F1053,Table9[Product_ID],Table9[Category],"Missing Catogory") -> Beverages | I1053: STR081 | J1053: =_xlfn.XLOOKUP(Sales_Transactions!$I1053,Store!$A$2:$A$181,Store!$B$2:$B$181,"Missing Store") -> FreshMart Erode Crossing | K1053: =_xlfn.XLOOKUP(Sales_Transactions!$I1053,Store!$A$2:$A$181,Store!$D$2:$D$181,"East") -> South | L1053: EMP0031 | M1053: Ramesh Iyer | N1053: =_xlfn.XLOOKUP(Sales_Transactions!$L1053,Table12[Employee_ID],Table12[Department],"Missing Department") -> Cashier | O1053: 4 | P1053: 503.36 | Q1053: 20 | R1053: 402.69 | S1053: 1610.75 | T1053: 1559.2 | U1053: 51.55 | V1053: Debit Card | W1053: Not Returned | X1053: Online | Y1053: 15:40 | Z1053: Weekday
A1054: INV101452 | B1054: 45769 | C1054: CUST0441 | D1054: =_xlfn.XLOOKUP(Sales_Transactions!$C1054,Customer!$A$2:$A$701,Customer!$B$2:$B$701,"Missing") -> Hari Kumar | E1054: =_xlfn.XLOOKUP(Table14[[#This Row],[Customer_ID]],Table10[Customer_ID],Table10[Membership],"Missing Membership") -> Silver | F1054: PRD068 | G1054: =_xlfn.XLOOKUP(Sales_Transactions!$F1054,Products!$A$2:$A$151,Products!$B$2:$B$151,"missing product") -> Patanjali Shampoo 2kg | H1054: =_xlfn.XLOOKUP(Sales_Transactions!$F1054,Table9[Product_ID],Table9[Category],"Missing Catogory") -> Personal Care | I1054: STR161 | J1054: =_xlfn.XLOOKUP(Sales_Transactions!$I1054,Store!$A$2:$A$181,Store!$B$2:$B$181,"Missing Store") -> FreshMart Jaipur Hub | K1054: =_xlfn.XLOOKUP(Sales_Transactions!$I1054,Store!$A$2:$A$181,Store!$D$2:$D$181,"East") -> North | L1054: EMP0062 | M1054: Jaya Selvam | N1054: =_xlfn.XLOOKUP(Sales_Transactions!$L1054,Table12[Employee_ID],Table12[Department],"Missing Department") -> Operations | O1054: 3 | P1054: 232.2 | Q1054: 20 | R1054: 139.32 | S1054: 557.28 | T1054: 482.94 | U1054: 74.34 | V1054: Debit Card | W1054: Not Returned | X1054: In-Store | Y1054: 11:24 | Z1054: Weekday
A1055: INV101453 | B1055: 46004 | C1055: CUST0415 | D1055: =_xlfn.XLOOKUP(Sales_Transactions!$C1055,Customer!$A$2:$A$701,Customer!$B$2:$B$701,"Missing") -> Bharath Devi | E1055: =_xlfn.XLOOKUP(Table14[[#This Row],[Customer_ID]],Table10[Customer_ID],Table10[Membership],"Missing Membership") -> Gold | F1055: PRD084 | G1055: =_xlfn.XLOOKUP(Sales_Transactions!$F1055,Products!$A$2:$A$151,Products!$B$2:$B$151,"missing product") -> Local Farm Fresh Fruits Combo | H1055: =_xlfn.XLOOKUP(Sales_Transactions!$F1055,Table9[Product_ID],Table9[Category],"Missing Catogory") -> Fruits | I1055: STR030 | J1055: =_xlfn.XLOOKUP(Sales_Transactions!$I1055,Store!$A$2:$A$181,Store!$B$2:$B$181,"Missing Store") -> FreshMart Mysuru Bypass | K1055: =_xlfn.XLOOKUP(Sales_Transactions!$I1055,Store!$A$2:$A$181,Store!$D$2:$D$181,"East") -> South | L1055: EMP0224 | M1055: Sathish Sekar | N1055: =_xlfn.XLOOKUP(Sales_Transactions!$L1055,Table12[Employee_ID],Table12[Department],"Missing Department") -> Operations | O1055: 6 | P1055: 242.93 | Q1055: 0 | R1055: 0 | S1055: 1676.22 | T1055: 1093.02 | U1055: 583.2 | V1055: Debit Card | W1055: Not Returned | X1055: In-Store | Y1055: 17:39 | Z1055: Weekend
A1056: INV101456 | B1056: 45983 | C1056: CUST0321 | D1056: =_xlfn.XLOOKUP(Sales_Transactions!$C1056,Customer!$A$2:$A$701,Customer!$B$2:$B$701,"Missing") -> Yamuna Mudaliar | E1056: =_xlfn.XLOOKUP(Table14[[#This Row],[Customer_ID]],Table10[Customer_ID],Table10[Membership],"Missing Membership") -> Silver | F1056: PRD012 | G1056: =_xlfn.XLOOKUP(Sales_Transactions!$F1056,Products!$A$2:$A$151,Products!$B$2:$B$151,"missing product") -> Harvest Gold Rusk 1kg | H1056: =_xlfn.XLOOKUP(Sales_Transactions!$F1056,Table9[Product_ID],Table9[Category],"Missing Catogory") -> Bakery | I1056: STR092 | J1056: =_xlfn.XLOOKUP(Sales_Transactions!$I1056,Store!$A$2:$A$181,Store!$B$2:$B$181,"Missing Store") -> FreshMart Chennai Gardens | K1056: =_xlfn.XLOOKUP(Sales_Transactions!$I1056,Store!$A$2:$A$181,Store!$D$2:$D$181,"East") -> South | L1056: EMP0122 | M1056: Rajesh Chettiar | N1056: =_xlfn.XLOOKUP(Sales_Transactions!$L1056,Table12[Employee_ID],Table12[Department],"Missing Department") -> Cashier | O1056: 5 | P1056: 541.35 | Q1056: 5 | R1056: 135.34 | S1056: 2957.12 | T1056: 1682 | U1056: 1275.12 | V1056: Debit Card | W1056: Not Returned | X1056: In-Store | Y1056: 15:49 | Z1056: Weekend
A1057: INV101459 | B1057: 45940 | C1057: CUST0278 | D1057: =_xlfn.XLOOKUP(Sales_Transactions!$C1057,Customer!$A$2:$A$701,Customer!$B$2:$B$701,"Missing") -> Umesh Nair | E1057: =_xlfn.XLOOKUP(Table14[[#This Row],[Customer_ID]],Table10[Customer_ID],Table10[Membership],"Missing Membership") -> Silver | F1057: PRD057 | G1057: =_xlfn.XLOOKUP(Sales_Transactions!$F1057,Products!$A$2:$A$151,Products!$B$2:$B$151,"missing product") -> Parle Chocolates 500g | H1057: =_xlfn.XLOOKUP(Sales_Transactions!$F1057,Table9[Product_ID],Table9[Category],"Missing Catogory") -> Snacks | I1057: STR071 | J1057: =_xlfn.XLOOKUP(Sales_Transactions!$I1057,Store!$A$2:$A$181,Store!$B$2:$B$181,"Missing Store") -> FreshMart Salem Crossing | K1057: =_xlfn.XLOOKUP(Sales_Transactions!$I1057,Store!$A$2:$A$181,Store!$D$2:$D$181,"East") -> South | L1057: EMP0120 | M1057: Mala Rao | N1057: =_xlfn.XLOOKUP(Sales_Transactions!$L1057,Table12[Employee_ID],Table12[Department],"Missing Department") -> Cashier | O1057: 3 | P1057: 317.99 | Q1057: 0 | R1057: 0 | S1057: 953.97 | T1057: 705.15 | U1057: 248.82 | V1057: Debit Card | W1057: Not Returned | X1057: In-Store | Y1057: 09:42 | Z1057: Weekday
... A1062: INV101473 | B1062: 46037 | C1062: CUST0244 | D1062: =_xlfn.XLOOKUP(Sales_Transactions!$C1062,Customer!$A$2:$A$701,Customer!$B$2:$B$701,"Missing") -> Padma Naicker | E1062: =_xlfn.XLOOKUP(Table14[[#This Row],[Customer_ID]],Table10[Customer_ID],Table10[Membership],"Missing Membership") -> Silver | F1062: PRD004 | G1062: =_xlfn.XLOOKUP(Sales_Transactions!$F1062,Products!$A$2:$A$151,Products!$B$2:$B$151,"missing product") -> Britannia Buns 2kg | H1062: =_xlfn.XLOOKUP(Sales_Transactions!$F1062,Table9[Product_ID],Table9[Category],"Missing Catogory") -> Bakery | I1062: STR057 | J1062: =_xlfn.XLOOKUP(Sales_Transactions!$I1062,Store!$A$2:$A$181,Store!$B$2:$B$181,"Missing Store") -> FreshMart Madurai Point | K1062: =_xlfn.XLOOKUP(Sales_Transactions!$I1062,Store!$A$2:$A$181,Store!$D$2:$D$181,"East") -> South | L1062: EMP0065 | M1062: Kavya Velan | N1062: =_xlfn.XLOOKUP(Sales_Transactions!$L1062,Table12[Employee_ID],Table12[Department],"Missing Department") -> Cashier | O1062: 1 | P1062: 398.25 | Q1062: 15 | R1062: 59.74 | S1062: 338.51 | T1062: 236.54 | U1062: 101.97 | V1062: Debit Card | W1062: Not Returned | X1062: In-Store | Y1062: 20:49 | Z1062: Weekday
A1063: INV101474 | B1063: 45807 | C1063: CUST0673 | D1063: =_xlfn.XLOOKUP(Sales_Transactions!$C1063,Customer!$A$2:$A$701,Customer!$B$2:$B$701,"Missing") -> Hari Sharma | E1063: =_xlfn.XLOOKUP(Table14[[#This Row],[Customer_ID]],Table10[Customer_ID],Table10[Membership],"Missing Membership") -> Silver | F1063: PRD014 | G1063: =_xlfn.XLOOKUP(Sales_Transactions!$F1063,Products!$A$2:$A$151,Products!$B$2:$B$151,"missing product") -> Milky Mist Curd 1kg | H1063: =_xlfn.XLOOKUP(Sales_Transactions!$F1063,Table9[Product_ID],Table9[Category],"Missing Catogory") -> Dairy | I1063: STR024 | J1063: =_xlfn.XLOOKUP(Sales_Transactions!$I1063,Store!$A$2:$A$181,Store!$B$2:$B$181,"Missing Store") -> FreshMart Bengaluru Plaza | K1063: =_xlfn.XLOOKUP(Sales_Transactions!$I1063,Store!$A$2:$A$181,Store!$D$2:$D$181,"East") -> South | L1063: EMP0133 | M1063: Deepak Naicker | N1063: =_xlfn.XLOOKUP(Sales_Transactions!$L1063,Table12[Employee_ID],Table12[Department],"Missing Department") -> Sales | O1063: 2 | P1063: 434.65 | Q1063: 20 | R1063: 173.86 | S1063: Rs.695.44 | T1063: 703.26 | U1063: -7.82 | V1063: Debit Card | W1063: Not Returned | X1063: In-Store | Y1063: 14:35 | Z1063: Weekday
A1064: INV101478 | B1064: 45943 | C1064: CUST0651 | D1064: =_xlfn.XLOOKUP(Sales_Transactions!$C1064,Customer!$A$2:$A$701,Customer!$B$2:$B$701,"Missing") -> Ilango Mudaliar | E1064: =_xlfn.XLOOKUP(Table14[[#This Row],[Customer_ID]],Table10[Customer_ID],Table10[Membership],"Missing Membership") -> Bronze | F1064: PRD056 | G1064: =_xlfn.XLOOKUP(Sales_Transactions!$F1064,Products!$A$2:$A$151,Products!$B$2:$B$151,"missing product") -> Cadbury Namkeen Combo | H1064: =_xlfn.XLOOKUP(Sales_Transactions!$F1064,Table9[Product_ID],Table9[Category],"Missing Catogory") -> Snacks | I1064: STR075 | J1064: =_xlfn.XLOOKUP(Sales_Transactions!$I1064,Store!$A$2:$A$181,Store!$B$2:$B$181,"Missing Store") -> FreshMart Salem Main Road | K1064: =_xlfn.XLOOKUP(Sales_Transactions!$I1064,Store!$A$2:$A$181,Store!$D$2:$D$181,"East") -> South | L1064: EMP0171 | M1064: Ashok Nair | N1064: =_xlfn.XLOOKUP(Sales_Transactions!$L1064,Table12[Employee_ID],Table12[Department],"Missing Department") -> Cashier | O1064: 3 | P1064: 333.54 | Q1064: 5 | R1064: 50.03 | S1064: 950.59 | T1064: 715.29 | U1064: 235.3 | V1064: Debit Card | W1064: Not Returned | X1064: In-Store | Y1064: 14:44 | Z1064: Weekday
A1065: INV101482 | B1065: 45943 | C1065: CUST0685 | D1065: =_xlfn.XLOOKUP(Sales_Transactions!$C1065,Customer!$A$2:$A$701,Customer!$B$2:$B$701,"Missing") -> Naveen Achari | E1065: =_xlfn.XLOOKUP(Table14[[#This Row],[Customer_ID]],Table10[Customer_ID],Table10[Membership],"Missing Membership") -> Gold | F1065: PRD049 | G1065: =_xlfn.XLOOKUP(Sales_Transactions!$F1065,Products!$A$2:$A$151,Products!$B$2:$B$151,"missing product") -> Cadbury Chips 1kg | H1065: =_xlfn.XLOOKUP(Sales_Transactions!$F1065,Table9[Product_ID],Table9[Category],"Missing Catogory") -> Snacks | I1065: STR055 | J1065: =_xlfn.XLOOKUP(Sales_Transactions!$I1065,Store!$A$2:$A$181,Store!$B$2:$B$181,"Missing Store") -> FreshMart Madurai Circle | K1065: =_xlfn.XLOOKUP(Sales_Transactions!$I1065,Store!$A$2:$A$181,Store!$D$2:$D$181,"East") -> South | L1065: EMP0068 | M1065: Manoj Subramaniam | N1065: =_xlfn.XLOOKUP(Sales_Transactions!$L1065,Table12[Employee_ID],Table12[Department],"Missing Department") -> Sales | O1065: 4 | P1065: 420.54 | Q1065: 0 | R1065: 0 | S1065: 1682.16 | T1065: 1235.76 | U1065: 446.4 | V1065: Debit Card | W1065: Not Returned | X1065: In-Store | Y1065: 12:20 | Z1065: Weekday
A1066: INV101493 | B1066: 45922 | C1066: CUST0433 | D1066: =_xlfn.XLOOKUP(Sales_Transactions!$C1066,Customer!$A$2:$A$701,Customer!$B$2:$B$701,"Missing") -> Uma Nair | E1066: =_xlfn.XLOOKUP(Table14[[#This Row],[Customer_ID]],Table10[Customer_ID],Table10[Membership],"Missing Membership") -> Gold | F1066: PRD035 | G1066: =_xlfn.XLOOKUP(Sales_Transactions!$F1066,Products!$A$2:$A$151,Products!$B$2:$B$151,"missing product") -> Coca-Cola Coffee 500g | H1066: =_xlfn.XLOOKUP(Sales_Transactions!$F1066,Table9[Product_ID],Table9[Category],"Missing Catogory") -> Beverages | I1066: STR057 | J1066: =_xlfn.XLOOKUP(Sales_Transactions!$I1066,Store!$A$2:$A$181,Store!$B$2:$B$181,"Missing Store") -> FreshMart Madurai Point | K1066: =_xlfn.XLOOKUP(Sales_Transactions!$I1066,Store!$A$2:$A$181,Store!$D$2:$D$181,"East") -> South | L1066: EMP0225 | M1066: Banu Achari | N1066: =_xlfn.XLOOKUP(Sales_Transactions!$L1066,Table12[Employee_ID],Table12[Department],"Missing Department") -> Sales | O1066: 8 | P1066: 509.6 | Q1066: 5 | R1066: 203.84 | S1066: 3872.96 | T1066: 3118.4 | U1066: 754.56 | V1066: Debit Card | W1066: Not Returned | X1066: Online | Y1066: 14:54 | Z1066: Weekday
A1067: INV101504 | B1067: 45990 | C1067: CUST0343 | D1067: =_xlfn.XLOOKUP(Sales_Transactions!$C1067,Customer!$A$2:$A$701,Customer!$B$2:$B$701,"Missing") -> Jayakumar Nathan | E1067: =_xlfn.XLOOKUP(Table14[[#This Row],[Customer_ID]],Table10[Customer_ID],Table10[Membership],"Missing Membership") -> Silver | F1067: PRD021 | G1067: =_xlfn.XLOOKUP(Sales_Transactions!$F1067,Products!$A$2:$A$151,Products!$B$2:$B$151,"missing product") -> Milky Mist Butter Pack | H1067: =_xlfn.XLOOKUP(Sales_Transactions!$F1067,Table9[Product_ID],Table9[Category],"Missing Catogory") -> Dairy | I1067: STR155 | J1067: =_xlfn.XLOOKUP(Sales_Transactions!$I1067,Store!$A$2:$A$181,Store!$B$2:$B$181,"Missing Store") -> FreshMart Delhi Complex | K1067: =_xlfn.XLOOKUP(Sales_Transactions!$I1067,Store!$A$2:$A$181,Store!$D$2:$D$181,"East") -> North | L1067: EMP0175 | M1067: Dinesh Reddy | N1067: =_xlfn.XLOOKUP(Sales_Transactions!$L1067,Table12[Employee_ID],Table12[Department],"Missing Department") -> Sales | O1067: 4 | P1067: 38.66 | Q1067: 0 | R1067: 0 | S1067: 177.84 | T1067: 129.6 | U1067: 48.24 | V1067: Debit Card | W1067: Not Returned | X1067: In-Store | Y1067: 14:29 | Z1067: Weekend
A1068: INV101505 | B1068: 46075 | C1068: CUST0402 | D1068: =_xlfn.XLOOKUP(Sales_Transactions!$C1068,Customer!$A$2:$A$701,Customer!$B$2:$B$701,"Missing") -> Usha Raj | E1068: =_xlfn.XLOOKUP(Table14[[#This Row],[Customer_ID]],Table10[Customer_ID],Table10[Membership],"Missing Membership") -> Gold | F1068: PRD084 | G1068: =_xlfn.XLOOKUP(Sales_Transactions!$F1068,Products!$A$2:$A$151,Products!$B$2:$B$151,"missing product") -> Local Farm Fresh Fruits Combo | H1068: =_xlfn.XLOOKUP(Sales_Transactions!$F1068,Table9[Product_ID],Table9[Category],"Missing Catogory") -> Fruits | I1068: STR013 | J1068: =_xlfn.XLOOKUP(Sales_Transactions!$I1068,Store!$A$2:$A$181,Store!$B$2:$B$181,"Missing Store") -> FreshMart Tiruppur Extension | K1068: =_xlfn.XLOOKUP(Sales_Transactions!$I1068,Store!$A$2:$A$181,Store!$D$2:$D$181,"East") -> South | L1068: EMP0077 | M1068: Senthil Subramaniam | N1068: =_xlfn.XLOOKUP(Sales_Transactions!$L1068,Table12[Employee_ID],Table12[Department],"Missing Department") -> Cashier | O1068: 7 | P1068: 228.59 | Q1068: 10 | R1068: 160.01 | S1068: 1656.14 | T1068: 1275.19 | U1068: 380.95 | V1068: Debit Card | W1068: Not Returned | X1068: Mobile App | Y1068: 09:48 | Z1068: Weekend
A1069: INV101518 | B1069: 45786 | C1069: CUST0627 | D1069: =_xlfn.XLOOKUP(Sales_Transactions!$C1069,Customer!$A$2:$A$701,Customer!$B$2:$B$701,"Missing") -> Ishwarya Mudaliar | E1069: =_xlfn.XLOOKUP(Table14[[#This Row],[Customer_ID]],Table10[Customer_ID],Table10[Membership],"Missing Membership") -> Silver | F1069: PRD019 | G1069: =_xlfn.XLOOKUP(Sales_Transactions!$F1069,Products!$A$2:$A$151,Products!$B$2:$B$151,"missing product") -> Amul Paneer 1kg | H1069: =_xlfn.XLOOKUP(Sales_Transactions!$F1069,Table9[Product_ID],Table9[Category],"Missing Catogory") -> Dairy | I1069: STR003 | J1069: =_xlfn.XLOOKUP(Sales_Transactions!$I1069,Store!$A$2:$A$181,Store!$B$2:$B$181,"Missing Store") -> FreshMart Tiruppur Square | K1069: =_xlfn.XLOOKUP(Sales_Transactions!$I1069,Store!$A$2:$A$181,Store!$D$2:$D$181,"East") -> South | L1069: EMP0298 | M1069: Balaji Reddy | N1069: =_xlfn.XLOOKUP(Sales_Transactions!$L1069,Table12[Employee_ID],Table12[Department],"Missing Department") -> Billing | O1069: 3 | P1069: 448.94 | Q1069: 10 | R1069: 134.68 | S1069: 1212.14 | T1069: 1140.24 | U1069: 71.9 | V1069: Debit Card | W1069: Not Returned | X1069: In-Store | Y1069: 10:30 | Z1069: Weekday
...

Sheet Sheet5
A3: Row Labels | B3: Sum of Sales_Amount | C3: Sum of Profit | D3: Sum of Quantity
A4: East | B4: 62655.19 | C4: 15527.09 | D4: 212
A5: Missing Region | B5: 2665.21 | C5: 683.88 | D5: 7
A6: North | B6: 246937.59 | C6: 65782.36 | D6: 872
A7: South | B7: 1869722.7 | C7: 474801.35 | D7: 6476
A8: West | B8: 686451.93 | C8: 180564.21 | D8: 2256
A9: Grand Total | B9: 2868432.6 | C9: 737358.89 | D9: 9823
B27: Regional Sales Performance

Sheet Sheet6
F2: Category Sales & Profit
A3: Row Labels | B3: Sum of Sales_Amount | C3: Sum of Profit | D3: Sum of Quantity
A4: Bakery | B4: 343694.76 | C4: 143483.76 | D4: 812
A5: Beverages | B5: 471195.53 | C5: 117031.27 | D5: 1571
A6: Cleaning | B6: 97873.45 | C6: 27123.8 | D6: 437
A7: Dairy | B7: 351546.11 | C7: 74650.33 | D7: 1203
A8: Frozen Foods | B8: 53359.36 | C8: 8413.38 | D8: 255
A9: Fruits | B9: 206014.11 | C9: 39093.44 | D9: 683
A10: Household | B10: 144591.68 | C10: 35467.75 | D10: 553
A11: Masala | B11: 153158.06 | C11: 41220.14 | D11: 487
A12: Oil | B12: 124504.98 | C12: 19200.85 | D12: 565
A13: Personal Care | B13: 192624.16 | C13: 61117.96 | D13: 599
A14: Rice | B14: 167384.1 | C14: 30185.16 | D14: 681
A15: Snacks | B15: 287706.41 | C15: 84119.62 | D15: 993
... A17: Grand Total | B17: 2812166.4 | C17: 721884.69 | D17: 9632

Sheet Sheet7
A3: Row Labels | B3: Sum of Sales_Amount | C3: Sum of Profit | D3: Count of Invoice_Number
A4: In-Store | B4: 1969380.3 | C4: 504060.82 | D4: 1738
A5: Mobile App | B5: 286557.95 | C5: 74107.63 | D5: 237
A6: Online | B6: 612494.35 | C6: 159190.44 | D6: 525
A7: Grand Total | B7: 2868432.6 | C7: 737358.89 | D7: 2500
B25: Sales Channel Performance

Sheet Sheet8
A3: Row Labels | B3: Sum of Sales_Amount | C3: Sum of Profit | D3: Sum of Quantity
A4: Coca-Cola Coffee 500g | B4: 78629.02 | C4: 20159.02 | D4: 150
A5: Harvest Gold Rusk 1kg | B5: 75156.97 | C5: 28902.89 | D5: 153
A6: Lays Namkeen 2kg | B6: 53010.1 | C6: 17706.3 | D6: 103
A7: Local Farm Fresh Vegetables 200g | B7: 46278.18 | C7: 9037.92 | D7: 123
A8: Nescafe Coffee 1kg | B8: 68998.76 | C8: 19301.51 | D8: 201
A9: Nescafe Coffee Pack | B9: 56784.24 | C9: 13571.22 | D9: 159
A10: Nescafe Soft Drinks Pack | B10: 62694.19 | C10: 16965.71 | D10: 152
A11: Nestle Curd 1kg | B11: 62189.96 | C11: 13328.34 | D11: 128
A12: Pepsi Tea 200g | B12: 53709.63 | C12: 13245.28 | D12: 164
A13: Tata Tea Soft Drinks 500g | B13: 53103.27 | C13: 11255.97 | D13: 135
A14: Grand Total | B14: 610554.32 | C14: 163474.16 | D14: 1468
A32: Top 10 Products

Sheet KPI VALUES
A3: Row Labels | B3: Sum of Profit | C3: Sum of Quantity
A4: 37.41 | B4: 0.76 | C4: 1
A5: 37.79 | B5: 5.39 | C5: 1
A6: 38.66 | B6: 6.26 | C6: 1
A7: 44.46 | B7: 24.12 | C7: 2
A8: 45.38 | B8: 2.37 | C8: 1
A9: 47.94 | B9: -0.21 | C9: 1
A10: 48.76 | B10: 22.56 | C10: 2
A11: 50.17 | B11: 12.69 | C11: 1
A12: 51.35 | B12: 6.39 | C12: 1
A13: 53.93 | B13: 5.78 | C13: 1
A14: 54.56 | B14: 9.6 | C14: 1
A15: 55.81 | B15: 10.85 | C15: 1
... A2279: 5419.04 | B2279: 2669.84 | C2279: 8
A2280: Rs.135.45 | B2280: 16.71 | C2280: 2
A2281: Rs.1407.12 | B2281: 391.8 | C2281: 4
A2282: Rs.1958.68 | B2282: 1034.98 | C2282: 5
A2283: Rs.2042.7 | B2283: 451.94 | C2283: 4
A2284: Rs.2375.73 | B2284: 547.19 | C2284: 7
A2285: Rs.2612.06 | B2285: 927.9 | C2285: 8
A2286: Rs.3105.4 | B2286: 514.14 | C2286: 7
A2287: Rs.3752.77 | B2287: 1098.44 | C2287: 7
A2288: Rs.402.16 | B2288: 54.43 | C2288: 3
A2289: Rs.4555.82 | B2289: 1864.62 | C2289: 8
A2290: Rs.695.44 | B2290: -7.82 | C2290: 2
A2291: Rs.716.85 | B2291: 243.77 | C2291: 2
... A2295: Grand Total | B2295: 737358.89 | C2295: 9823

Sheet Sheet12
